workingFiles/countDown.v
module countDown(
    input wire clk, // 1hz
    input wire countDownActive,

    output reg [3:0] s10,
    output reg [3:0] s1
    );

    reg [1:0] activeSet;

    initial 
    begin
        activeSet <= 2'b00;
        s10 <= 7;
        s1 <= 9;
    end

    always @(posedge clk) 
    begin
        activeSet <= {activeSet[0], countDownActive};
        if(activeSet == 2'b01)
        begin
            s10 <= 6;
            s1 <= 0;
        end
        else if(countDownActive && ((s1 != 0) || (s10 != 0)))
        begin
            if (s1 === 0)
            begin
                s10 <= s10 - 1;
                s1 <= 9;
            end
            else
            begin
                s1 <= s1 - 1;
            end
        end
        else if(~countDownActive)
        begin
            s10 <= 7;
            s1 <= 9;    
        end
    end



endmodule

display2.v
`timescale 10ns / 1ns

module display2(
    input wire clk1KHz,
    input wire digit1,      // Digit 1 input
    input wire digit2,      // Digit 2 input
    output reg [3:0] seg,   // 7-segment display output
    output reg an           // 2-digit select output (anode control)
);

    reg digit_select;           // low for Digit 1, High for Digit 2

    always @(posedge clk1KHz) begin
        case (digit_select)
            1'b0: begin
                // Display minutes tens digit (m10)
                an = 1'b0;  // Only first digit active
                case (digit1)
                    1'b0: seg = 7'b1000000; // 0
                    1'b1: seg = 7'b1111001; // 1
                endcase
            end
            1'b1: begin
                // Display minutes ones digit (m1)
                an = 1'b1;  // Only second digit active
                case (digit2)
                    1'b0: seg = 7'b1000000;
                    1'b1: seg = 7'b1111001;
                endcase
            end
        endcase
        // Cycle through the digits (m10, m1, s10, s1) with multiplexing
        digit_select <= digit_select + 1;
        if (digit_select > 1'b1) digit_select <= 1'b0;
    end

endmodule

display.v
`timescale 10ns / 1ns

module display(
    input wire clk1KHz,
    input wire [3:0] digit1,  // Digit 1 input
    input wire [3:0] digit2,  // Digit 2 input
    input wire [3:0] digit3,  // Digit 3 input
    input wire [3:0] digit4,  // Digit 4 input 
    output reg [3:0] seg,     // 7-segment display output
    output reg [3:0] an       // 4-digit select output (anode control)
);

    reg [1:0] digit_select;   // For digit multiplexing (0: m10, 1: m1, 2: s10, 3: s1)

    // Multiplexing 7-segment decoder
    always @(posedge clk1KHz) begin
        // Check if all digits are zero (no input case)
        // if (digit1 == 4'b0000 && digit2 == 4'b0000 && digit3 == 4'b0000 && digit4 == 4'b0000) begin
        //     seg = 7'b1111111;  // Display nothing (blank) if no input
        // end else begin
            case (digit_select)
                2'b00: begin
                    // Display minutes tens digit (m10)
                    an = 4'b0111;  // Only m10 is active
                    case (digit1)
                        4'b0000: seg = 7'b1000000; // 0
                        4'b0001: seg = 7'b1111001; // 1
                        4'b0010: seg = 7'b0100100; // 2
                        4'b0011: seg = 7'b0110000; // 3
                        4'b0100: seg = 7'b0011001; // 4
                        4'b0101: seg = 7'b0010010; // 5
                        4'b0110: seg = 7'b0000010; // 6
                        4'b0111: seg = 7'b1111000; // 7
                        4'b1000: seg = 7'b0000000; // 8
                        4'b1001: seg = 7'b0010000; // 9
                        4'b1010: seg = 7'b0001000; // A
                        4'b1011: seg = 7'b0000011; // B
                        4'b1100: seg = 7'b1000110; // C
                        4'b1101: seg = 7'b0100001; // D
                        4'b1110: seg = 7'b0000110; // E
                        4'b1111: seg = 7'b0001110; // F
                    endcase
                end
                2'b01: begin
                    // Display minutes ones digit (m1)
                    an = 4'b1011;  // Only m1 is active
                    case (digit2)
                        4'b0000: seg = 7'b1000000;
                        4'b0001: seg = 7'b1111001;
                        4'b0010: seg = 7'b0100100;
                        4'b0011: seg = 7'b0110000;
                        4'b0100: seg = 7'b0011001;
                        4'b0101: seg = 7'b0010010;
                        4'b0110: seg = 7'b0000010;
                        4'b0111: seg = 7'b1111000;
                        4'b1000: seg = 7'b0000000;
                        4'b1001: seg = 7'b0010000;
                        4'b1010: seg = 7'b0001000; // A
                        4'b1011: seg = 7'b0000011; // B
                        4'b1100: seg = 7'b1000110; // C
                        4'b1101: seg = 7'b0100001; // D
                        4'b1110: seg = 7'b0000110; // E
                        4'b1111: seg = 7'b0001110; // F
                    endcase
                end
                2'b10: begin
                    // Display seconds tens digit (s10)
                    an = 4'b1101;  // Only s10 is active
                    case (digit3)
                        4'b0000: seg = 7'b1000000;
                        4'b0001: seg = 7'b1111001;
                        4'b0010: seg = 7'b0100100;
                        4'b0011: seg = 7'b0110000;
                        4'b0100: seg = 7'b0011001;
                        4'b0101: seg = 7'b0010010;
                        4'b0110: seg = 7'b0000010;
                        4'b0111: seg = 7'b1111000;
                        4'b1000: seg = 7'b0000000;
                        4'b1001: seg = 7'b0010000;
                        4'b1010: seg = 7'b0001000; // A
                        4'b1011: seg = 7'b0000011; // B
                        4'b1100: seg = 7'b1000110; // C
                        4'b1101: seg = 7'b0100001; // D
                        4'b1110: seg = 7'b0000110; // E
                        4'b1111: seg = 7'b0001110; // F
                    endcase
                end
                2'b11: begin
                    // Display seconds ones digit (s1)
                    an = 4'b1110;  // Only s1 is active
                    case (digit4)
                        4'b0000: seg = 7'b1000000;
                        4'b0001: seg = 7'b1111001;
                        4'b0010: seg = 7'b0100100;
                        4'b0011: seg = 7'b0110000;
                        4'b0100: seg = 7'b0011001;
                        4'b0101: seg = 7'b0010010;
                        4'b0110: seg = 7'b0000010;
                        4'b0111: seg = 7'b1111000;
                        4'b1000: seg = 7'b0000000;
                        4'b1001: seg = 7'b0010000;
                        4'b1010: seg = 7'b0001000; // A
                        4'b1011: seg = 7'b0000011; // B
                        4'b1100: seg = 7'b1000110; // C
                        4'b1101: seg = 7'b0100001; // D
                        4'b1110: seg = 7'b0000110; // E
                        4'b1111: seg = 7'b0001110; // F
                    endcase
                end
            endcase
        // end
        
        // Cycle through the digits (m10, m1, s10, s1) with multiplexing
        digit_select <= digit_select + 1;
        if (digit_select > 2'b11) digit_select <= 2'b00;
    end
endmodule

workingFiles/displayHandle.v
module displayHandle(
    input wire clk, // 1hz
    input wire clk1KHz, //1khz
    input wire flag,
    input wire flagSelect,
    input wire lock,

    output reg flagResolve,
    output reg locker,

    output wire [3:0] seg,     // 7-segment display output
    output wire [3:0] an,       // 4-digit select output (anode control)

    output wire [3:0]seg2,
    output wire an2
    );

    reg prevLockState;

    reg countDownActive;
    wire [3:0] s10;
    wire [3:0] s1;

    reg smallDisplay10;
    reg smallDisplay1;

    display my_Display(
        .clk1KHz(clk1KHz),
        .digit1(4'b0000),  // Digit 1 input
        .digit2(4'b0000),  // Digit 2 input
        .digit3(s10),  // Digit 3 input
        .digit4(s1),  // Digit 4 input 
        .seg(seg),     // 7-segment display output
        .an(an)       // 4-digit select output (anode control)
    );

    
    display2 my_display2(
        .clk1KHz(clk1KHz),
        .digit1(smallDisplay10),  // Digit 1 input (1 bit)
        .digit2(smallDisplay1),  // Digit 2 input (1 bit)
        .seg(seg2),     // 7-segment display output
        .an(an2)       // 4-digit select output (anode control)
    );
    

    countDown my_CountDown(
        .clk(clk), // 1hz
        .countDownActive(countDownActive),

        .s10(s10),
        .s1(s1)
    );

    initial 
    begin
        flagResolve <= 0;
        countDownActive <= 0;
        locker <= 0;
        smallDisplay10 <= 1;
        smallDisplay1 <= 1;
        prevLockState <= 1;
    end

    always @(posedge clk) 
    begin
        prevLockState <= lock;
       if(flag && ~flagSelect)
       begin
            // wrong password 
            smallDisplay10 <= 0;
            smallDisplay1 <= 0;

            flagResolve <= 1;
       end
       else if(flag && flagSelect && ~flagResolve)
       begin
            // 3 failed attempts 
            if(~countDownActive)
            begin
                countDownActive <= 1;
                smallDisplay10 <= 0;
                smallDisplay1 <= 0;
                $display("Count down activated");
            end
            else if(s10 == 0 && s1 == 0)
            begin   
                smallDisplay10 <= 1;
                smallDisplay1 <= 1;
                flagResolve <= 1;
                countDownActive <= 0;
            end
       end
       else
       begin
            flagResolve <= 0;
       end

       if (~lock && ~locker) begin
            if(~countDownActive)
            begin
                smallDisplay10 <= 0;
                smallDisplay1 <= 1;
                countDownActive <= 1;
            end
            else if(s10 == 0 && s1 == 0)
            begin   
                locker <= 1;
                smallDisplay10 <= 1;
                smallDisplay1 <= 1;
                countDownActive <= 0;
            end
       end
       else if(~prevLockState && lock)
       begin
            smallDisplay10 <= 1;
            smallDisplay1 <= 1;
       end
       else
        begin
            locker <= 0;
        end
    end



endmodule

unlocker.v
module unlocker(
    input wire clk, 
    input wire locker, 

    input wire btn1,
    input wire btn2,
    input wire btn3,
    input wire btn4,
    input wire btn5,
    input wire switch1, // ==0 : guest account // ==1 : user account 

    input wire [3:0] inputCount,
    

    input wire [3:0] userNameInput0,
    input wire [3:0] userNameInput1,
    input wire [3:0] userNameInput2,
    input wire [3:0] userNameInput3,

    input wire[3:0] passwordInput0,
    input wire[3:0] passwordInput1,
    input wire[3:0] passwordInput2,
    input wire[3:0] passwordInput3,

    input wire flagResolve, //indicates that the flag has been delt with 

    output reg lock,
    output reg flag,        //when flag goes up error = incorrect password 
    output reg flagSelect,     //flagSelect = 0: wrong password attempt, flagSelect = 1: 3 incorrect attempts 
    output reg resetCount   //tell other module to reset inputCount to 0, also means input is not going to get read

    );

    reg [15:0] userList [7:0];    // Array of 8 elements, each 20 bits wide
    reg [15:0] userPassword [7:0]; // Array of 8 elements, each 20 bits wide
    reg [1:0] userMode [7:0];      // 0=admin, 1=user, 2=guest

    reg[15:0] tempUser;
    reg[15:0] tempPassword;

    integer userCount;
    
    integer currentUser;

    integer loginAttempts;

    integer i;

    initial 
    begin
        userList[0] <= 16'b0001000100000000;
        userPassword[0] <= 16'b0001000100000000;
        userMode[0] <= 2'b00;
        currentUser <= 0;
        userCount <= 1;
        lock <= 1;
        loginAttempts <= 0;
        lockout <= 0;
    end

    always @(posedge clk) 
    begin
        if(flag && flagResolve)
        begin
            flagSelect <= 0;
            flag <= 0;
        end
        if(~lock)
        begin
            if(locker || btn1)
            begin
                if(userMode[currentUser] == 2)
                begin
                    // remove current user 
                    userCount <= userCount - 1;
                    userList[currentUser][15:0] <= userList[userCount][15:0];
                    userPassword[currentUser][15:0] <= userPassword[userCount][15:0];
                    userMode[currentUser] <= userMode[userCount];
                end
                lock <= 1;
                resetCount <= 0;
            end
            else if(userMode[currentUser][1:0] == 2'b00 || userMode[currentUser][1:0] == 2'b01)
            begin
                if(btn2)
                begin
                    // reset password
                    resetCount <= 0;
                    if(inputCount == 4)
                    begin
                        userPassword[currentUser][15:0] <= {userNameInput3[3:0], userNameInput2[3:0], userNameInput1[3:0], userNameInput0[3:0]};
                        // $display("New password: %b", userPassword[currentUser][19:0]);
                        resetCount <= 1;
                    end
                    
                    
                end
                else if(userMode[currentUser][1:0] == 2'b00)
                begin
                    if(btn3)
                    begin
                        // add user 
                        resetCount <= 0;
                        if(inputCount == 8)
                        begin
                            if(userCount < 8)
                            begin
                                userList[userCount] <= {userNameInput3[3:0], userNameInput2[3:0], userNameInput1[3:0], userNameInput0[3:0]};
                                userPassword[userCount] <= {passwordInput3[3:0], passwordInput2[3:0], passwordInput1[3:0], passwordInput0[3:0]};
                                if(switch1)
                                begin
                                    userMode[userCount] <= 1;
                                end
                                else
                                begin
                                    userMode[userCount] <= 2;
                                end
                                resetCount <= 1;
                                userCount <= userCount + 1;
                            end
                            else
                            begin
                                // alert too many usres
                                // flag <= 1;
                            end
                        end
                    end
                    else if(btn4)
                    begin
                        // change password
                        resetCount <= 0;
                        if(inputCount == 8)
                        begin
                            resetCount <= 1;
                            for(i=0; i<userCount; i=i+1)
                            begin
                                tempUser <= userList[i][15:0];
                                tempPassword <= userPassword[i][15:0];
                                if(tempUser[3:0] == userNameInput0 && tempUser[7:4] == userNameInput1 && tempUser[11:8] == userNameInput2 && tempUser[15:12] == userNameInput3)
                                begin
                                    userPassword[i] <= {passwordInput3[3:0], passwordInput2[3:0], passwordInput1[3:0], passwordInput0[3:0]};
                                end
                            end
                        end

                    end
                    else if(btn5)
                    begin
                        // delete user 
                        resetCount <= 0;
                        if(inputCount == 4)
                        begin
                            resetCount <= 1;
                            for(i=0; i<userCount; i=i+1)
                            begin
                                tempUser <= userList[i][15:0];
                                tempPassword <= userPassword[i][15:0];
                                if(tempUser[3:0] == userNameInput0 && tempUser[7:4] == userNameInput1 && tempUser[11:8] == userNameInput2 && tempUser[15:12] == userNameInput3)
                                begin
                                    userCount <= userCount - 1;
                                    userList[i][15:0] <= userList[userCount][15:0];
                                    userPassword[i][15:0] <= userPassword[userCount][15:0];
                                    userMode[i] <= userMode[userCount];
                                end
                            end
                        end
                    end
                end
            end
        end
        else if(inputCount == 8)
        begin
            for(i=0; i<userCount; i=i+1)
            begin
                tempUser <= userList[i][19:0];
                tempPassword <= userPassword[i][19:0];
                if(tempUser[3:0] == userNameInput0 && tempUser[7:4] == userNameInput1 && tempUser[11:8] == userNameInput2 && tempUser[15:12] == userNameInput3)
                begin
                    if(tempPassword[3:0] == passwordInput0 && tempPassword[7:4] == passwordInput1 && tempPassword[11:8] == passwordInput2 && tempPassword[15:12] == passwordInput3)
                    begin
                        currentUser <= i;
                        lock <= 0;
                        resetCount <= 1;
                        loginAttempts <= 0;
                    end
                    else
                    begin
                        loginAttempts <= loginAttempts + 1;
                        flag <= 1;
                        if(loginAttempts == 3)
                        begin
                            flagSelect <= 1;
                            loginAttempts <= 0;
                        end
                        else
                        begin
                            flagSelect <= 0;
                        end
                    end;
                end
            end
        end
        
    end



endmodule

workingFiles/mainDriver_tb.v
module mainDriver_tb;
    reg clk;

    reg btn1;
    reg btn2;
    reg btn3;
    reg btn4;
    reg btn5;

    reg switch1;

    reg [3:0] inputCount;

    reg [3:0] userNameInput0;
    reg [3:0] userNameInput1;
    reg [3:0] userNameInput2;
    reg [3:0] userNameInput3;

    reg[3:0] passwordInput0;
    reg[3:0] passwordInput1;
    reg[3:0] passwordInput2;
    reg[3:0] passwordInput3;

    
    wire resetCount;

    wire [3:0] seg;     // 7-segment display output
    wire [3:0] an;       // 4-digit select output (anode control)

    wire [3:0] seg2;
    wire an2;

    reg[3:0] checkCount;

    unlocker my_unlock(
        .clk(clk),
        .locker(locker), 
        .btn1(btn1),
        .btn2(btn2),
        .btn3(btn3),
        .btn4(btn4),
        .btn5(btn5),
        .switch1(switch1),
        .inputCount(inputCount), 
        .userNameInput0(userNameInput0), 
        .userNameInput1(userNameInput1), 
        .userNameInput2(userNameInput2), 
        .userNameInput3(userNameInput3), 
        .passwordInput0(passwordInput0), 
        .passwordInput1(passwordInput1), 
        .passwordInput2(passwordInput2), 
        .passwordInput3(passwordInput3), 
        .flagResolve(flagResolve),
        .lock(lock),
        .flag(flag),
        .flagSelect(flagSelect),
        .resetCount(resetCount)
    );

    displayHandle myDisplayHandle(
        .clk(clk),
        .clk1KHz(clk),
        .flag(flag),
        .flagSelect(flagSelect),
        .lock(lock),

        .flagResolve(flagResolve),
        .locker(locker),
        .seg(seg),     // 7-segment display output
        .an(an),        // 4-digit select output
        .seg2(seg2),
        .an2(an2)
    );

    initial begin
        $dumpfile("wave.vcd");
        $dumpvars(0, mainDriver_tb);
        $display("Waveform created");

        clk = 0;
        checkCount = 1;
        //== incorrect password check ==//
        userNameInput0 = 0;
        inputCount = 1;
        #1;
        userNameInput1 = 0;
        inputCount = 2;
        #1;
        userNameInput2 = 1;
        inputCount = 3;
        #1;
        userNameInput3 = 1;
        inputCount = 4;
        
        #1;
        passwordInput0 = 1;
        inputCount = 5;
        #1;
        passwordInput1 = 0;
        inputCount = 6;
        #1;
        passwordInput2 = 1;
        inputCount = 7;
        #1;
        passwordInput3 = 1;
        inputCount = 8;
        #1;

        checkCount = 2;
        //== lockout check ==//
        //incorrect 1
        userNameInput0 = 0;
        inputCount = 1;
        #1;
        userNameInput1 = 0;
        inputCount = 2;
        #1;
        userNameInput2 = 1;
        inputCount = 3;
        #1;
        userNameInput3 = 1;
        inputCount = 4;
        
        #1;
        passwordInput0 = 1;
        inputCount = 5;
        #1;
        passwordInput1 = 0;
        inputCount = 6;
        #1;
        passwordInput2 = 1;
        inputCount = 7;
        #1;
        passwordInput3 = 1;
        inputCount = 8;
        #1;

        //incorrect 2
        userNameInput0 = 0;
        inputCount = 1;
        #1;
        userNameInput1 = 0;
        inputCount = 2;
        #1;
        userNameInput2 = 1;
        inputCount = 3;
        #1;
        userNameInput3 = 1;
        inputCount = 4;
        
        #1;
        passwordInput0 = 1;
        inputCount = 5;
        #1;
        passwordInput1 = 0;
        inputCount = 6;
        #1;
        passwordInput2 = 1;
        inputCount = 7;
        #1;
        passwordInput3 = 1;
        inputCount = 8;
        #1;

        //incorrect 3
        userNameInput0 = 0;
        inputCount = 1;
        #1;
        userNameInput1 = 0;
        inputCount = 2;
        #1;
        userNameInput2 = 1;
        inputCount = 3;
        #1;
        userNameInput3 = 1;
        inputCount = 4;
        
        #1;
        passwordInput0 = 1;
        inputCount = 5;
        #1;
        passwordInput1 = 0;
        inputCount = 6;
        #1;
        passwordInput2 = 1;
        inputCount = 7;
        #1;
        passwordInput3 = 1;
        inputCount = 8;
        #1;
        inputCount = 0;

        checkCount = checkCount + 1;
        //==check to see if use is locked out, should keep user locked out
        userNameInput0 = 0;
        inputCount = 1;
        #1;
        userNameInput1 = 0;
        inputCount = 2;
        #1;
        userNameInput2 = 1;
        inputCount = 3;
        #1;
        userNameInput3 = 1;
        inputCount = 4;
        
        #1;
        passwordInput0 = 0;
        inputCount = 5;
        #1;
        passwordInput1 = 0;
        inputCount = 6;
        #1;
        passwordInput2 = 1;
        inputCount = 7;
        #1;
        passwordInput3 = 1;
        inputCount = 8;
        #1;
        inputCount = 0;

        checkCount = checkCount + 1;
        //==log in after, and start count down for auto lock
        #150;
        inputCount = 8;
        #2;
        inputCount = 0;
        #150;
        


        #15 $finish;
    end

    always begin
        #0.5 clk = ~clk;
    end
endmodule

prevWaveForms/check_2D_display_wave.vcd
$date
	Wed Mar 12 00:10:47 2025
$end
$version
	Icarus Verilog
$end
$timescale
	1ns
$end
$scope module mainDriver_tb $end
$var wire 4 ! seg2 [3:0] $end
$var wire 4 " seg [3:0] $end
$var wire 1 # resetCount $end
$var wire 1 $ locker $end
$var wire 1 % lock $end
$var wire 1 & flagSelect $end
$var wire 1 ' flagResolve $end
$var wire 1 ( flag $end
$var wire 1 ) an2 $end
$var wire 4 * an [3:0] $end
$var reg 1 + btn1 $end
$var reg 1 , btn2 $end
$var reg 1 - btn3 $end
$var reg 1 . btn4 $end
$var reg 1 / btn5 $end
$var reg 4 0 checkCount [3:0] $end
$var reg 1 1 clk $end
$var reg 4 2 inputCount [3:0] $end
$var reg 4 3 passwordInput0 [3:0] $end
$var reg 4 4 passwordInput1 [3:0] $end
$var reg 4 5 passwordInput2 [3:0] $end
$var reg 4 6 passwordInput3 [3:0] $end
$var reg 1 7 switch1 $end
$var reg 4 8 userNameInput0 [3:0] $end
$var reg 4 9 userNameInput1 [3:0] $end
$var reg 4 : userNameInput2 [3:0] $end
$var reg 4 ; userNameInput3 [3:0] $end
$scope module myDisplayHandle $end
$var wire 1 1 clk $end
$var wire 1 1 clk1KHz $end
$var wire 4 < seg2 [3:0] $end
$var wire 4 = seg [3:0] $end
$var wire 4 > s10 [3:0] $end
$var wire 4 ? s1 [3:0] $end
$var wire 1 % lock $end
$var wire 1 & flagSelect $end
$var wire 1 ( flag $end
$var wire 1 ) an2 $end
$var wire 4 @ an [3:0] $end
$var reg 1 A countDownActive $end
$var reg 1 ' flagResolve $end
$var reg 1 $ locker $end
$var reg 1 B prevLockState $end
$var reg 1 C smallDisplay1 $end
$var reg 1 D smallDisplay10 $end
$scope module my_CountDown $end
$var wire 1 1 clk $end
$var wire 1 A countDownActive $end
$var reg 2 E activeSet [1:0] $end
$var reg 4 F s1 [3:0] $end
$var reg 4 G s10 [3:0] $end
$upscope $end
$scope module my_Display $end
$var wire 1 1 clk1KHz $end
$var wire 4 H digit1 [3:0] $end
$var wire 4 I digit2 [3:0] $end
$var wire 4 J digit3 [3:0] $end
$var wire 4 K digit4 [3:0] $end
$var reg 4 L an [3:0] $end
$var reg 2 M digit_select [1:0] $end
$var reg 4 N seg [3:0] $end
$upscope $end
$scope module my_display2 $end
$var wire 1 1 clk1KHz $end
$var wire 1 D digit1 $end
$var wire 1 C digit2 $end
$var reg 1 ) an $end
$var reg 1 O digit_select $end
$var reg 4 P seg [3:0] $end
$upscope $end
$upscope $end
$scope module my_unlock $end
$var wire 1 + btn1 $end
$var wire 1 , btn2 $end
$var wire 1 - btn3 $end
$var wire 1 . btn4 $end
$var wire 1 / btn5 $end
$var wire 1 1 clk $end
$var wire 1 ' flagResolve $end
$var wire 4 Q inputCount [3:0] $end
$var wire 1 $ locker $end
$var wire 4 R passwordInput0 [3:0] $end
$var wire 4 S passwordInput1 [3:0] $end
$var wire 4 T passwordInput2 [3:0] $end
$var wire 4 U passwordInput3 [3:0] $end
$var wire 1 7 switch1 $end
$var wire 4 V userNameInput0 [3:0] $end
$var wire 4 W userNameInput1 [3:0] $end
$var wire 4 X userNameInput2 [3:0] $end
$var wire 4 Y userNameInput3 [3:0] $end
$var reg 1 ( flag $end
$var reg 1 & flagSelect $end
$var reg 1 % lock $end
$var reg 1 # resetCount $end
$var reg 16 Z tempPassword [15:0] $end
$var reg 16 [ tempUser [15:0] $end
$var integer 32 \ currentUser [31:0] $end
$var integer 32 ] i [31:0] $end
$var integer 32 ^ loginAttempts [31:0] $end
$var integer 32 _ userCount [31:0] $end
$upscope $end
$upscope $end
$enddefinitions $end
$comment Show the parameter values. $end
$dumpall
$end
#0
$dumpvars
b1 _
b0 ^
bx ]
b0 \
bx [
bx Z
bx Y
bx X
bx W
b0 V
bx U
bx T
bx S
bx R
b1 Q
bx P
0O
bx N
b0 M
bx L
b1001 K
b111 J
b0 I
b0 H
b111 G
b1001 F
b0 E
1D
1C
1B
0A
bx @
b1001 ?
b111 >
bx =
bx <
bx ;
bx :
bx 9
b0 8
x7
bx 6
bx 5
bx 4
bx 3
b1 2
01
b1 0
x/
x.
x-
x,
x+
bx *
x)
0(
0'
0&
1%
0$
x#
bx "
bx !
$end
#5
b1 M
1O
b0 "
b0 =
b0 N
b111 *
b111 @
b111 L
b1001 !
b1001 <
b1001 P
0)
11
#10
01
b10 2
b10 Q
b0 9
b0 W
#15
0O
b10 M
1)
b1011 *
b1011 @
b1011 L
11
#20
01
b11 2
b11 Q
b1 :
b1 X
#25
b11 M
1O
b1000 "
b1000 =
b1000 N
b1101 *
b1101 @
b1101 L
0)
11
#30
01
b100 2
b100 Q
b1 ;
b1 Y
#35
0O
b0 M
1)
b0 "
b0 =
b0 N
b1110 *
b1110 @
b1110 L
11
#40
01
b101 2
b101 Q
b1 3
b1 R
#45
b1 M
1O
b111 *
b111 @
b111 L
0)
11
#50
01
b110 2
b110 Q
b0 4
b0 S
#55
0O
b10 M
1)
b1011 *
b1011 @
b1011 L
11
#60
01
b111 2
b111 Q
b1 5
b1 T
#65
b11 M
1O
b1000 "
b1000 =
b1000 N
b1101 *
b1101 @
b1101 L
0)
11
#70
01
b1000 2
b1000 Q
b1 6
b1 U
#75
0O
b0 M
b1000100000000 Z
b1000100000000 [
1)
b0 "
b0 =
b0 N
b1110 *
b1110 @
b1110 L
b1 ]
11
#80
01
b1 2
b1 Q
b10 0
#85
b1 M
1O
b111 *
b111 @
b111 L
0)
11
#90
01
b10 2
b10 Q
#95
0O
b10 M
1)
b1011 *
b1011 @
b1011 L
11
#100
01
b11 2
b11 Q
#105
b11 M
1O
b1000 "
b1000 =
b1000 N
b1101 *
b1101 @
b1101 L
0)
11
#110
01
b100 2
b100 Q
#115
0O
b0 M
1)
b0 "
b0 =
b0 N
b1110 *
b1110 @
b1110 L
11
#120
01
b101 2
b101 Q
#125
b1 M
1O
b111 *
b111 @
b111 L
0)
11
#130
01
b110 2
b110 Q
#135
0O
b10 M
1)
b1011 *
b1011 @
b1011 L
11
#140
01
b111 2
b111 Q
#145
b11 M
1O
b1000 "
b1000 =
b1000 N
b1101 *
b1101 @
b1101 L
0)
11
#150
01
b1000 2
b1000 Q
#155
0O
b0 M
b1 ^
1(
1)
b0 "
b0 =
b0 N
b1110 *
b1110 @
b1110 L
b1 ]
11
#160
01
b1 2
b1 Q
#165
b1 M
1O
1'
0C
0D
b111 *
b111 @
b111 L
0)
11
#170
01
b10 2
b10 Q
#175
0O
b10 M
0(
b0 !
b0 <
b0 P
1)
b1011 *
b1011 @
b1011 L
11
#180
01
b11 2
b11 Q
#185
b11 M
1O
0'
b1000 "
b1000 =
b1000 N
b1101 *
b1101 @
b1101 L
0)
11
#190
01
b100 2
b100 Q
#195
0O
b0 M
1)
b0 "
b0 =
b0 N
b1110 *
b1110 @
b1110 L
11
#200
01
b101 2
b101 Q
#205
b1 M
1O
b111 *
b111 @
b111 L
0)
11
#210
01
b110 2
b110 Q
#215
0O
b10 M
1)
b1011 *
b1011 @
b1011 L
11
#220
01
b111 2
b111 Q
#225
b11 M
1O
b1000 "
b1000 =
b1000 N
b1101 *
b1101 @
b1101 L
0)
11
#230
01
b1000 2
b1000 Q
#235
0O
b0 M
b10 ^
1(
1)
b0 "
b0 =
b0 N
b1110 *
b1110 @
b1110 L
b1 ]
11
#240
01
b1 2
b1 Q
#245
b1 M
1O
1'
b111 *
b111 @
b111 L
0)
11
#250
01
b10 2
b10 Q
#255
0O
b10 M
0(
1)
b1011 *
b1011 @
b1011 L
11
#260
01
b11 2
b11 Q
#265
b11 M
1O
0'
b1000 "
b1000 =
b1000 N
b1101 *
b1101 @
b1101 L
0)
11
#270
01
b100 2
b100 Q
#275
0O
b0 M
1)
b0 "
b0 =
b0 N
b1110 *
b1110 @
b1110 L
11
#280
01
b101 2
b101 Q
#285
b1 M
1O
b111 *
b111 @
b111 L
0)
11
#290
01
b110 2
b110 Q
#295
0O
b10 M
1)
b1011 *
b1011 @
b1011 L
11
#300
01
b111 2
b111 Q
#305
b11 M
1O
b1000 "
b1000 =
b1000 N
b1101 *
b1101 @
b1101 L
0)
11
#310
01
b1000 2
b1000 Q
#315
0O
b0 M
b0 ^
1&
1(
1)
b0 "
b0 =
b0 N
b1110 *
b1110 @
b1110 L
b1 ]
11
#320
01
b11 0
b1 2
b1 Q
#325
b1 M
1O
1A
b111 *
b111 @
b111 L
0)
11
#330
01
b10 2
b10 Q
#335
b1000 ?
b1000 F
b1000 K
b1 E
0O
b10 M
1)
b1011 *
b1011 @
b1011 L
11
#340
01
b11 2
b11 Q
#345
b11 M
1O
b0 ?
b0 F
b0 K
b110 >
b110 G
b110 J
b11 E
b1000 "
b1000 =
b1000 N
b1101 *
b1101 @
b1101 L
0)
11
#350
01
b100 2
b100 Q
#355
b1001 ?
b1001 F
b1001 K
b101 >
b101 G
b101 J
0O
b0 M
1)
b0 "
b0 =
b0 N
b1110 *
b1110 @
b1110 L
11
#360
01
b101 2
b101 Q
b0 3
b0 R
#365
b1 M
1O
b1000 ?
b1000 F
b1000 K
b111 *
b111 @
b111 L
0)
11
#370
01
b110 2
b110 Q
#375
b111 ?
b111 F
b111 K
0O
b10 M
1)
b1011 *
b1011 @
b1011 L
11
#380
01
b111 2
b111 Q
#385
b11 M
1O
b110 ?
b110 F
b110 K
b10 "
b10 =
b10 N
b1101 *
b1101 @
b1101 L
0)
11
#390
01
b1000 2
b1000 Q
#395
b101 ?
b101 F
b101 K
0O
b0 M
1)
b1110 *
b1110 @
b1110 L
11
#400
01
b100 0
b0 2
b0 Q
#405
b1 M
1O
b100 ?
b100 F
b100 K
b0 "
b0 =
b0 N
b111 *
b111 @
b111 L
0)
11
#410
01
#415
b11 ?
b11 F
b11 K
0O
b10 M
1)
b1011 *
b1011 @
b1011 L
11
#420
01
#425
b11 M
1O
b10 ?
b10 F
b10 K
b10 "
b10 =
b10 N
b1101 *
b1101 @
b1101 L
0)
11
#430
01
#435
b1 ?
b1 F
b1 K
0O
b0 M
1)
b100 "
b100 =
b100 N
b1110 *
b1110 @
b1110 L
11
#440
01
#445
b1 M
1O
b0 ?
b0 F
b0 K
b0 "
b0 =
b0 N
b111 *
b111 @
b111 L
0)
11
#450
01
#455
b1001 ?
b1001 F
b1001 K
b100 >
b100 G
b100 J
0O
b10 M
1)
b1011 *
b1011 @
b1011 L
11
#460
01
#465
b11 M
1O
b1000 ?
b1000 F
b1000 K
b1001 "
b1001 =
b1001 N
b1101 *
b1101 @
b1101 L
0)
11
#470
01
#475
b111 ?
b111 F
b111 K
0O
b0 M
1)
b0 "
b0 =
b0 N
b1110 *
b1110 @
b1110 L
11
#480
01
#485
b1 M
1O
b110 ?
b110 F
b110 K
b111 *
b111 @
b111 L
0)
11
#490
01
#495
b101 ?
b101 F
b101 K
0O
b10 M
1)
b1011 *
b1011 @
b1011 L
11
#500
01
#505
b11 M
1O
b100 ?
b100 F
b100 K
b1001 "
b1001 =
b1001 N
b1101 *
b1101 @
b1101 L
0)
11
#510
01
#515
b11 ?
b11 F
b11 K
0O
b0 M
1)
b1110 *
b1110 @
b1110 L
11
#520
01
#525
b1 M
1O
b10 ?
b10 F
b10 K
b0 "
b0 =
b0 N
b111 *
b111 @
b111 L
0)
11
#530
01
#535
b1 ?
b1 F
b1 K
0O
b10 M
1)
b1011 *
b1011 @
b1011 L
11
#540
01
#545
b11 M
1O
b0 ?
b0 F
b0 K
b1001 "
b1001 =
b1001 N
b1101 *
b1101 @
b1101 L
0)
11
#550
01
#555
b1001 ?
b1001 F
b1001 K
b11 >
b11 G
b11 J
0O
b0 M
1)
b0 "
b0 =
b0 N
b1110 *
b1110 @
b1110 L
11
#560
01
#565
b1 M
1O
b1000 ?
b1000 F
b1000 K
b111 *
b111 @
b111 L
0)
11
#570
01
#575
b111 ?
b111 F
b111 K
0O
b10 M
1)
b1011 *
b1011 @
b1011 L
11
#580
01
#585
b11 M
1O
b110 ?
b110 F
b110 K
b1101 *
b1101 @
b1101 L
0)
11
#590
01
