unlocker.v
module unlocker(
    input wire clk, 
    input wire locker, 

    input wire btn1,
    input wire btn2,
    input wire btn3,
    input wire btn4,
    input wire btn5,
    input wire switch1, // ==0 : guest account // ==1 : user account 

    input wire [3:0] inputCount,
    

    input wire [4:0] userNameInput0,
    input wire [4:0] userNameInput1,
    input wire [4:0] userNameInput2,
    input wire [4:0] userNameInput3,

    input wire[4:0] passwordInput0,
    input wire[4:0] passwordInput1,
    input wire[4:0] passwordInput2,
    input wire[4:0] passwordInput3,

    input wire flagResolve,

    output reg lock,
    output reg flag,        //when flag goes up error = incorrect password 
    output reg resetCount
    );

    reg [19:0] userList [7:0];    // Array of 8 elements, each 20 bits wide
    reg [19:0] userPassword [7:0]; // Array of 8 elements, each 20 bits wide
    reg [1:0] userMode [7:0];      // 0=admin, 1=user, 2=guest

    reg[19:0] tempUser;
    reg[19:0] tempPassword;

    integer userCount;
    
    integer currentUser;

    integer i;

    initial 
    begin
        userList[0] = 20'b00001000010000000000;
        userPassword[0] = 20'b00001000010000000000;
        userMode[0] = 2'b00;
        currentUser = 0;
        userCount = 1;
        lock = 1;
    end

    always @(posedge clk) 
    begin
        if(flag && flagResolve)
        begin
            flag = 0;
        end
        if(~lock)
        begin
            if(locker || btn1)
            begin
                if(userMode[currentUser] == 2)
                begin
                    // remove current user 
                    userCount = userCount - 1;
                    userList[currentUser][19:0] = userList[userCount][19:0];
                    userPassword[currentUser][19:0] = userPassword[userCount][19:0];
                    userMode[currentUser] = userMode[userCount];
                end
                lock = 1;
                resetCount = 0;
            end
            else if(userMode[currentUser][1:0] == 2'b00 || userMode[currentUser][1:0] == 2'b01)
            begin
                if(btn2)
                begin
                    // reset password
                    resetCount = 0;
                    if(inputCount == 4)
                    begin
                        userPassword[currentUser][19:0] = {userNameInput3[4:0], userNameInput2[4:0], userNameInput1[4:0], userNameInput0[4:0]};
                        // $display("New password: %b", userPassword[currentUser][19:0]);
                        resetCount = 1;
                    end
                    
                    
                end
                else if(userMode[currentUser][1:0] == 2'b00)
                begin
                    if(btn3)
                    begin
                        // add user 
                        resetCount = 0;
                        if(inputCount == 8)
                        begin
                            if(userCount < 8)
                            begin
                                userList[userCount] = {userNameInput3[4:0], userNameInput2[4:0], userNameInput1[4:0], userNameInput0[4:0]};
                                userPassword[userCount] = {passwordInput3[4:0], passwordInput2[4:0], passwordInput1[4:0], passwordInput0[4:0]};
                                if(switch1)
                                begin
                                    userMode[userCount] = 1;
                                end
                                else
                                begin
                                    userMode[userCount] = 2;
                                end
                                resetCount = 1;
                                userCount = userCount + 1;
                            end
                            else
                            begin
                                // alert too many usres
                                flag = 1;
                            end
                        end
                    end
                    else if(btn4)
                    begin
                        // change password
                        resetCount = 0;
                        if(inputCount == 8)
                        begin
                            resetCount = 1;
                            for(i=0; i<userCount; i=i+1)
                            begin
                                tempUser = userList[i][19:0];
                                tempPassword = userPassword[i][19:0];
                                if(tempUser[4:0] == userNameInput0 && tempUser[9:5] == userNameInput1 && tempUser[14:10] == userNameInput2 && tempUser[19:15] == userNameInput3)
                                begin
                                    userPassword[i] = {passwordInput3[4:0], passwordInput2[4:0], passwordInput1[4:0], passwordInput0[4:0]};
                                end
                            end
                        end

                    end
                    else if(btn5)
                    begin
                        // delete user 
                        resetCount = 0;
                        if(inputCount == 4)
                        begin
                            resetCount = 1;
                            for(i=0; i<userCount; i=i+1)
                            begin
                                tempUser = userList[i][19:0];
                                tempPassword = userPassword[i][19:0];
                                if(tempUser[4:0] == userNameInput0 && tempUser[9:5] == userNameInput1 && tempUser[14:10] == userNameInput2 && tempUser[19:15] == userNameInput3)
                                begin
                                    userCount = userCount - 1;
                                    userList[i][19:0] = userList[userCount][19:0];
                                    userPassword[i][19:0] = userPassword[userCount][19:0];
                                    userMode[i] = userMode[userCount];
                                end
                            end
                        end
                    end
                end
            end
        end
        else if(inputCount == 8)
        begin
            for(i=0; i<userCount; i=i+1)
            begin
                tempUser = userList[i][19:0];
                tempPassword = userPassword[i][19:0];
                if(tempUser[4:0] == userNameInput0 && tempUser[9:5] == userNameInput1 && tempUser[14:10] == userNameInput2 && tempUser[19:15] == userNameInput3)
                begin
                    if(tempPassword[4:0] == passwordInput0 && tempPassword[9:5] == passwordInput1 && tempPassword[14:10] == passwordInput2 && tempPassword[19:15] == passwordInput3)
                    begin
                        currentUser = i;
                        lock = 0;
                        resetCount = 1;
                    end
                    else
                    begin
                        flag = 1;
                    end;
                end
            end
        end
        
    end



endmodule

unlocker_tb.v
module unlocker_tb;
    reg clk;
    reg locker;

    reg btn1;
    reg btn2;
    reg btn3;
    reg btn4;
    reg btn5;

    reg switch1;

    reg [3:0] inputCount;

    reg [4:0] userNameInput0;
    reg [4:0] userNameInput1;
    reg [4:0] userNameInput2;
    reg [4:0] userNameInput3;

    reg[4:0] passwordInput0;
    reg[4:0] passwordInput1;
    reg[4:0] passwordInput2;
    reg[4:0] passwordInput3;

    reg flagResolve;

    wire lock;
    wire flag;
    wire resetCount;

    reg[3:0] checkCount;

    unlocker my_unlock(
        .clk(clk),
        .locker(locker), 
        .btn1(btn1),
        .btn2(btn2),
        .btn3(btn3),
        .btn4(btn4),
        .btn5(btn5),
        .switch1(switch1),
        .inputCount(inputCount), 
        .userNameInput0(userNameInput0), 
        .userNameInput1(userNameInput1), 
        .userNameInput2(userNameInput2), 
        .userNameInput3(userNameInput3), 
        .passwordInput0(passwordInput0), 
        .passwordInput1(passwordInput1), 
        .passwordInput2(passwordInput2), 
        .passwordInput3(passwordInput3), 
        .flagResolve(flagResolve),
        .lock(lock),
        .flag(flag),
        .resetCount(resetCount)
        );

    initial begin
        $dumpfile("wave.vcd");
        $dumpvars(0, unlocker_tb);

        clk = 0;
        #10;
        
        checkCount = 0;
        //== incorrect password check ==//
        userNameInput0 = 0;
        inputCount = 1;
        #1;
        userNameInput1 = 0;
        inputCount = 2;
        #1;
        userNameInput2 = 1;
        inputCount = 3;
        #1;
        userNameInput3 = 1;
        inputCount = 4;
        
        #1;
        passwordInput0 = 0;
        inputCount = 5;
        #1;
        passwordInput1 = 1;
        inputCount = 6;
        #1;
        passwordInput2 = 1;
        inputCount = 7;
        #1;
        passwordInput3 = 0;
        inputCount = 8;
        #20;

        checkCount = 1;
        //== correct password check ==//
        userNameInput0 = 0;
        inputCount = 1;
        #1;
        userNameInput1 = 0;
        inputCount = 2;
        #1;
        userNameInput2 = 1;
        inputCount = 3;
        #1;
        userNameInput3 = 1;
        inputCount = 4;
        
        #1;
        passwordInput0 = 0;
        inputCount = 5;
        #1;
        passwordInput1 = 0;
        inputCount = 6;
        #1;
        passwordInput2 = 1;
        inputCount = 7;
        #1;
        passwordInput3 = 1;
        inputCount = 8;
        #20;

        checkCount = 1;
        //== log out check ==//
        //log out 
        btn1 = 1;
        inputCount = 0;
        #10
        btn1 = 0;
        #20;

        // attempt to log back in
        userNameInput0 = 0;
        inputCount = 1;
        #1;
        userNameInput1 = 0;
        inputCount = 2;
        #1;
        userNameInput2 = 1;
        inputCount = 3;
        #1;
        userNameInput3 = 1;
        inputCount = 4;
        
        #1;
        passwordInput0 = 0;
        inputCount = 5;
        #1;
        passwordInput1 = 0;
        inputCount = 6;
        #1;
        passwordInput2 = 1;
        inputCount = 7;
        #1;
        passwordInput3 = 1;
        inputCount = 8;
        #20;

        checkCount = 2;
        //== reset password check ==//
        btn2 = 1;
        inputCount = 0;
        #1;
        userNameInput0 = 2;
        inputCount = 1;
        #1;
        userNameInput1 = 0;
        inputCount = 2;
        #1;
        userNameInput2 = 1;
        inputCount = 3;
        #1;
        userNameInput3 = 1;
        inputCount = 4;
        #20;
        btn2 = 0;

        // log out 
        btn1 = 1;
        #10
        btn1 = 0;
        #20;

        // attempt old password 
        userNameInput0 = 0;
        inputCount = 1;
        #1;
        userNameInput1 = 0;
        inputCount = 2;
        #1;
        userNameInput2 = 1;
        inputCount = 3;
        #1;
        userNameInput3 = 1;
        inputCount = 4;
        
        #1;
        passwordInput0 = 0;
        inputCount = 5;
        #1;
        passwordInput1 = 0;
        inputCount = 6;
        #1;
        passwordInput2 = 1;
        inputCount = 7;
        #1;
        passwordInput3 = 1;
        inputCount = 8;
        #20;

        // new password 
        userNameInput0 = 0;
        inputCount = 1;
        #1;
        userNameInput1 = 0;
        inputCount = 2;
        #1;
        userNameInput2 = 1;
        inputCount = 3;
        #1;
        userNameInput3 = 1;
        inputCount = 4;
        
        #1;
        passwordInput0 = 2;
        inputCount = 5;
        #1;
        passwordInput1 = 0;
        inputCount = 6;
        #1;
        passwordInput2 = 1;
        inputCount = 7;
        #1;
        passwordInput3 = 1;
        inputCount = 8;
        #20;

        checkCount = 3;
        //== add new user check ==//
        //create account 
        btn3 = 1;
        inputCount = 0;
        #1;

        userNameInput0 = 1;
        inputCount = 1;
        switch1 = 1;
        #1;
        userNameInput1 = 2;
        inputCount = 2;
        #1;
        userNameInput2 = 3;
        inputCount = 3;
        #1;
        userNameInput3 = 4;
        inputCount = 4;
        
        #1;
        passwordInput0 = 2;
        inputCount = 5;
        #1;
        passwordInput1 = 7;
        inputCount = 6;
        #1;
        passwordInput2 = 1;
        inputCount = 7;
        #1;
        passwordInput3 = 1;
        inputCount = 8;
        #5;
        btn3=0;

        //logout 
        btn1 = 1;
        inputCount = 0;
        #10
        btn1 = 0;
        #20;
        

        //attempt log in
        userNameInput0 = 1;
        inputCount = 1;
        switch1 = 1;
        #1;
        userNameInput1 = 2;
        inputCount = 2;
        #1;
        userNameInput2 = 3;
        inputCount = 3;
        #1;
        userNameInput3 = 4;
        inputCount = 4;
        
        #1;
        passwordInput0 = 2;
        inputCount = 5;
        #1;
        passwordInput1 = 7;
        inputCount = 6;
        #1;
        passwordInput2 = 1;
        inputCount = 7;
        #1;
        passwordInput3 = 1;
        inputCount = 8;
        #5;

        checkCount = 4;
        //== switch password of other user ==//
        //log into admin account
        btn1 = 1;
        inputCount = 0;
        #10
        btn1 = 0;
        #1;
        userNameInput0 = 0;
        inputCount = 1;
        #1;
        userNameInput1 = 0;
        inputCount = 2;
        #1;
        userNameInput2 = 1;
        inputCount = 3;
        #1;
        userNameInput3 = 1;
        inputCount = 4;
        
        #1;
        passwordInput0 = 2;
        inputCount = 5;
        #1;
        passwordInput1 = 0;
        inputCount = 6;
        #1;
        passwordInput2 = 1;
        inputCount = 7;
        #1;
        passwordInput3 = 1;
        inputCount = 8;
        #20;

        //switch password 
        btn4 = 1;
        userNameInput0 = 1;
        inputCount = 1;
        #1;
        userNameInput1 = 2;
        inputCount = 2;
        #1;
        userNameInput2 = 3;
        inputCount = 3;
        #1;
        userNameInput3 = 4;
        inputCount = 4;
        
        #1;
        passwordInput0 = 2;
        inputCount = 5;
        #1;
        passwordInput1 = 7;
        inputCount = 6;
        #1;
        passwordInput2 = 9;
        inputCount = 7;
        #1;
        passwordInput3 = 1;
        inputCount = 8;
        #5;
        btn4 = 0;

        //check login
        btn1 = 1;
        inputCount = 0;
        #10
        btn1 = 0;
        #1;
        //old password 
        userNameInput0 = 1;
        inputCount = 1;
        #1;
        userNameInput1 = 2;
        inputCount = 2;
        #1;
        userNameInput2 = 3;
        inputCount = 3;
        #1;
        userNameInput3 = 4;
        inputCount = 4;
        
        #1;
        passwordInput0 = 2;
        inputCount = 5;
        #1;
        passwordInput1 = 7;
        inputCount = 6;
        #1;
        passwordInput2 = 1;
        inputCount = 7;
        #1;
        passwordInput3 = 1;
        inputCount = 8;
        #20;

        //correct password 
        inputCount = 0;
        userNameInput0 = 1;
        inputCount = 1;
        #1;
        userNameInput1 = 2;
        inputCount = 2;
        #1;
        userNameInput2 = 3;
        inputCount = 3;
        #1;
        userNameInput3 = 4;
        inputCount = 4;
        
        #1;
        passwordInput0 = 2;
        inputCount = 5;
        #1;
        passwordInput1 = 7;
        inputCount = 6;
        #1;
        passwordInput2 = 9;
        inputCount = 7;
        #1;
        passwordInput3 = 1;
        inputCount = 8;
        #5;

        checkCount = 5;
        //==test delete user
        //log into admin account
        btn1 = 1;
        inputCount = 0;
        #10
        btn1 = 0;
        #1;
        userNameInput0 = 0;
        inputCount = 1;
        #1;
        userNameInput1 = 0;
        inputCount = 2;
        #1;
        userNameInput2 = 1;
        inputCount = 3;
        #1;
        userNameInput3 = 1;
        inputCount = 4;
        
        #1;
        passwordInput0 = 2;
        inputCount = 5;
        #1;
        passwordInput1 = 0;
        inputCount = 6;
        #1;
        passwordInput2 = 1;
        inputCount = 7;
        #1;
        passwordInput3 = 1;
        inputCount = 8;
        #20;

        //delete last user 
        btn5 = 1;
        inputCount = 0;
        #1;
        userNameInput0 = 1;
        inputCount = 1;
        #1;
        userNameInput1 = 2;
        inputCount = 2;
        #1;
        userNameInput2 = 3;
        inputCount = 3;
        #1;
        userNameInput3 = 4;
        inputCount = 4;
        #5;
        btn5 = 0;

        //create guest account 
        btn3 = 1;
        inputCount = 0;
        #1;

        userNameInput0 = 1;
        inputCount = 1;
        switch1 = 0;
        #1;
        userNameInput1 = 5;
        inputCount = 2;
        #1;
        userNameInput2 = 3;
        inputCount = 3;
        #1;
        userNameInput3 = 4;
        inputCount = 4;
        
        #1;
        passwordInput0 = 2;
        inputCount = 5;
        #1;
        passwordInput1 = 7;
        inputCount = 6;
        #1;
        passwordInput2 = 1;
        inputCount = 7;
        #1;
        passwordInput3 = 1;
        inputCount = 8;
        #1;
        btn3=0;

        //attempt log in with deleted uesr
        btn1 = 1;
        inputCount = 0;
        #10
        btn1 = 0;
        #1;

        inputCount = 0;
        userNameInput0 = 1;
        inputCount = 1;
        #1;
        userNameInput1 = 2;
        inputCount = 2;
        #1;
        userNameInput2 = 3;
        inputCount = 3;
        #1;
        userNameInput3 = 4;
        inputCount = 4;
        
        #1;
        passwordInput0 = 2;
        inputCount = 5;
        #1;
        passwordInput1 = 7;
        inputCount = 6;
        #1;
        passwordInput2 = 9;
        inputCount = 7;
        #1;
        passwordInput3 = 1;
        inputCount = 8;
        #5;

        //log into guest account
        inputCount = 0;
        userNameInput0 = 1;
        inputCount = 1;
        switch1 = 0;
        #1;
        userNameInput1 = 5;
        inputCount = 2;
        #1;
        userNameInput2 = 3;
        inputCount = 3;
        #1;
        userNameInput3 = 4;
        inputCount = 4;
        
        #1;
        passwordInput0 = 2;
        inputCount = 5;
        #1;
        passwordInput1 = 7;
        inputCount = 6;
        #1;
        passwordInput2 = 1;
        inputCount = 7;
        #1;
        passwordInput3 = 1;
        inputCount = 8;
        #5;

        //attempt to log in again
        btn1 = 1;
        inputCount = 0;
        #10
        btn1 = 0;
        #5;

        userNameInput0 = 1;
        inputCount = 1;
        switch1 = 0;
        #1;
        userNameInput1 = 5;
        inputCount = 2;
        #1;
        userNameInput2 = 3;
        inputCount = 3;
        #1;
        userNameInput3 = 4;
        inputCount = 4;
        
        #1;
        passwordInput0 = 2;
        inputCount = 5;
        #1;
        passwordInput1 = 7;
        inputCount = 6;
        #1;
        passwordInput2 = 1;
        inputCount = 7;
        #1;
        passwordInput3 = 1;
        inputCount = 8;
        #5;


        #20 $finish;
    end

    always begin
        #0.5 clk = ~clk;
    end
endmodule

wave.vcd
$date
	Fri Mar  7 17:13:11 2025
$end
$version
	Icarus Verilog
$end
$timescale
	1s
$end
$scope module unlocker_tb $end
$var wire 1 ! resetCount $end
$var wire 1 " lock $end
$var wire 1 # flag $end
$var reg 1 $ btn1 $end
$var reg 1 % btn2 $end
$var reg 1 & btn3 $end
$var reg 1 ' btn4 $end
$var reg 1 ( btn5 $end
$var reg 4 ) checkCount [3:0] $end
$var reg 1 * clk $end
$var reg 1 + flagResolve $end
$var reg 4 , inputCount [3:0] $end
$var reg 1 - locker $end
$var reg 5 . passwordInput0 [4:0] $end
$var reg 5 / passwordInput1 [4:0] $end
$var reg 5 0 passwordInput2 [4:0] $end
$var reg 5 1 passwordInput3 [4:0] $end
$var reg 1 2 switch1 $end
$var reg 5 3 userNameInput0 [4:0] $end
$var reg 5 4 userNameInput1 [4:0] $end
$var reg 5 5 userNameInput2 [4:0] $end
$var reg 5 6 userNameInput3 [4:0] $end
$scope module my_unlock $end
$var wire 1 $ btn1 $end
$var wire 1 % btn2 $end
$var wire 1 & btn3 $end
$var wire 1 ' btn4 $end
$var wire 1 ( btn5 $end
$var wire 1 * clk $end
$var wire 1 + flagResolve $end
$var wire 4 7 inputCount [3:0] $end
$var wire 1 - locker $end
$var wire 5 8 passwordInput0 [4:0] $end
$var wire 5 9 passwordInput1 [4:0] $end
$var wire 5 : passwordInput2 [4:0] $end
$var wire 5 ; passwordInput3 [4:0] $end
$var wire 1 2 switch1 $end
$var wire 5 < userNameInput0 [4:0] $end
$var wire 5 = userNameInput1 [4:0] $end
$var wire 5 > userNameInput2 [4:0] $end
$var wire 5 ? userNameInput3 [4:0] $end
$var reg 1 # flag $end
$var reg 1 " lock $end
$var reg 1 ! resetCount $end
$var reg 20 @ tempPassword [19:0] $end
$var reg 20 A tempUser [19:0] $end
$var integer 32 B currentUser [31:0] $end
$var integer 32 C i [31:0] $end
$var integer 32 D userCount [31:0] $end
$upscope $end
$upscope $end
$enddefinitions $end
$comment Show the parameter values. $end
$dumpall
$end
#0
$dumpvars
b1 D
bx C
b0 B
bx A
bx @
bx ?
bx >
bx =
bx <
bx ;
bx :
bx 9
bx 8
bx 7
bx 6
bx 5
bx 4
bx 3
x2
bx 1
bx 0
bx /
bx .
x-
bx ,
x+
0*
bx )
x(
x'
x&
x%
x$
x#
1"
x!
$end
#1
1*
#2
0*
#3
1*
#4
0*
#5
1*
#6
0*
#7
1*
#8
0*
#9
1*
#10
0*
b1 ,
b1 7
b0 3
b0 <
b0 )
#11
1*
b10 ,
b10 7
b0 4
b0 =
#12
0*
b11 ,
b11 7
b1 5
b1 >
#13
1*
b100 ,
b100 7
b1 6
b1 ?
#14
0*
b101 ,
b101 7
b0 .
b0 8
#15
1*
b110 ,
b110 7
b1 /
b1 9
#16
0*
b111 ,
b111 7
b1 0
b1 :
#17
1#
b1000010000000000 @
b1000010000000000 A
b1 C
1*
b1000 ,
b1000 7
b0 1
b0 ;
#18
0*
#19
b1 C
1*
#20
0*
#21
b1 C
1*
#22
0*
#23
b1 C
1*
#24
0*
#25
b1 C
1*
#26
0*
#27
b1 C
1*
#28
0*
#29
b1 C
1*
#30
0*
#31
b1 C
1*
#32
0*
#33
b1 C
1*
#34
0*
#35
b1 C
1*
#36
0*
#37
1*
b1 ,
b1 7
b1 )
#38
0*
b10 ,
b10 7
#39
1*
b11 ,
b11 7
#40
0*
b100 ,
b100 7
#41
1*
b101 ,
b101 7
#42
0*
b110 ,
b110 7
b0 /
b0 9
#43
1*
b111 ,
b111 7
#44
0*
b1000 ,
b1000 7
b1 1
b1 ;
#45
1!
0"
b1 C
1*
#46
0*
#47
1*
#48
0*
#49
1*
#50
0*
#51
1*
#52
0*
#53
1*
#54
0*
#55
1*
#56
0*
#57
1*
#58
0*
#59
1*
#60
0*
#61
1*
#62
0*
#63
1*
#64
0*
b0 ,
b0 7
1$
#65
0!
1"
1*
#66
0*
#67
1*
#68
0*
#69
1*
#70
0*
#71
1*
#72
0*
#73
1*
#74
0*
0$
#75
1*
#76
0*
#77
1*
#78
0*
#79
1*
#80
0*
#81
1*
#82
0*
#83
1*
#84
0*
#85
1*
#86
0*
#87
1*
#88
0*
#89
1*
#90
0*
#91
1*
#92
0*
#93
1*
#94
0*
b1 ,
b1 7
#95
1*
b10 ,
b10 7
#96
0*
b11 ,
b11 7
#97
1*
b100 ,
b100 7
#98
0*
b101 ,
b101 7
#99
1*
b110 ,
b110 7
#100
0*
b111 ,
b111 7
#101
1!
0"
b1 C
1*
b1000 ,
b1000 7
#102
0*
#103
1*
#104
0*
#105
1*
#106
0*
#107
1*
#108
0*
#109
1*
#110
0*
#111
1*
#112
0*
#113
1*
#114
0*
#115
1*
#116
0*
#117
1*
#118
0*
#119
1*
#120
0*
#121
0!
1*
b0 ,
b0 7
1%
b10 )
#122
0*
b1 ,
b1 7
b10 3
b10 <
#123
1*
b10 ,
b10 7
#124
0*
b11 ,
b11 7
#125
1!
1*
b100 ,
b100 7
#126
0*
#127
1!
1*
#128
0*
#129
1!
1*
#130
0*
#131
1!
1*
#132
0*
#133
1!
1*
#134
0*
#135
1!
1*
#136
0*
#137
1!
1*
#138
0*
#139
1!
1*
#140
0*
#141
1!
1*
#142
0*
#143
1!
1*
#144
0*
#145
0!
1"
1*
1$
0%
#146
0*
#147
1*
#148
0*
#149
1*
#150
0*
#151
1*
#152
0*
#153
1*
#154
0*
#155
1*
0$
#156
0*
#157
1*
#158
0*
#159
1*
#160
0*
#161
1*
#162
0*
#163
1*
#164
0*
#165
1*
#166
0*
#167
1*
#168
0*
#169
1*
#170
0*
#171
1*
#172
0*
#173
1*
#174
0*
#175
1*
b1 ,
b1 7
b0 3
b0 <
#176
0*
b10 ,
b10 7
#177
1*
b11 ,
b11 7
#178
0*
b100 ,
b100 7
#179
1*
b101 ,
b101 7
#180
0*
b110 ,
b110 7
#181
1*
b111 ,
b111 7
#182
0*
b1000 ,
b1000 7
#183
b1000010000000010 @
b1 C
1*
#184
0*
#185
b1 C
1*
#186
0*
#187
b1 C
1*
#188
0*
#189
b1 C
1*
#190
0*
#191
b1 C
1*
#192
0*
#193
b1 C
1*
#194
0*
#195
b1 C
1*
#196
0*
#197
b1 C
1*
#198
0*
#199
b1 C
1*
#200
0*
#201
b1 C
1*
#202
0*
b1 ,
b1 7
#203
1*
b10 ,
b10 7
#204
0*
b11 ,
b11 7
#205
1*
b100 ,
b100 7
#206
0*
b101 ,
b101 7
b10 .
b10 8
#207
1*
b110 ,
b110 7
#208
0*
b111 ,
b111 7
#209
1!
0"
b1 C
1*
b1000 ,
b1000 7
#210
0*
#211
1*
#212
0*
#213
1*
#214
0*
#215
1*
#216
0*
#217
1*
#218
0*
#219
1*
#220
0*
#221
1*
#222
0*
#223
1*
#224
0*
#225
1*
#226
0*
#227
1*
#228
0*
#229
0!
1*
b0 ,
b0 7
1&
b11 )
#230
0*
12
b1 ,
b1 7
b1 3
b1 <
#231
1*
b10 ,
b10 7
b10 4
b10 =
#232
0*
b11 ,
b11 7
b11 5
b11 >
#233
1*
b100 ,
b100 7
b100 6
b100 ?
#234
0*
b101 ,
b101 7
#235
1*
b110 ,
b110 7
b111 /
b111 9
#236
0*
b111 ,
b111 7
#237
b10 D
1!
1*
b1000 ,
b1000 7
#238
0*
#239
b11 D
1!
1*
#240
0*
#241
b100 D
1!
1*
#242
0*
b0 ,
b0 7
1$
0&
#243
0!
1"
1*
#244
0*
#245
1*
#246
0*
#247
1*
#248
0*
#249
1*
#250
0*
#251
1*
#252
0*
0$
#253
1*
#254
0*
#255
1*
#256
0*
#257
1*
#258
0*
#259
1*
#260
0*
#261
1*
#262
0*
#263
1*
#264
0*
#265
1*
#266
0*
#267
1*
#268
0*
#269
1*
#270
0*
#271
1*
#272
0*
b1 ,
b1 7
#273
1*
b10 ,
b10 7
#274
0*
b11 ,
b11 7
#275
1*
b100 ,
b100 7
#276
0*
b101 ,
b101 7
#277
1*
b110 ,
b110 7
#278
0*
b111 ,
b111 7
#279
1!
0"
b11 B
b1000010011100010 @
b100000110001000001 A
b100 C
1*
b1000 ,
b1000 7
#280
0*
#281
1*
#282
0*
#283
1*
#284
0*
b0 ,
b0 7
1$
b100 )
#285
0!
1"
1*
#286
0*
#287
1*
#288
0*
#289
1*
#290
0*
#291
1*
#292
0*
#293
1*
#294
0*
0$
#295
1*
b1 ,
b1 7
b0 3
b0 <
#296
0*
b10 ,
b10 7
b0 4
b0 =
#297
1*
b11 ,
b11 7
b1 5
b1 >
#298
0*
b100 ,
b100 7
b1 6
b1 ?
#299
1*
b101 ,
b101 7
#300
0*
b110 ,
b110 7
b0 /
b0 9
#301
1*
b111 ,
b111 7
#302
0*
b1000 ,
b1000 7
#303
1!
0"
b0 B
b1000010011100010 @
b100000110001000001 A
b100 C
1*
#304
0*
#305
1*
#306
0*
#307
1*
#308
0*
#309
1*
#310
0*
#311
1*
#312
0*
#313
1*
#314
0*
#315
1*
#316
0*
#317
1*
#318
0*
#319
1*
#320
0*
#321
1*
#322
0*
b1 ,
b1 7
b1 3
b1 <
1'
#323
0!
1*
b10 ,
b10 7
b10 4
b10 =
#324
0*
b11 ,
b11 7
b11 5
b11 >
#325
1*
b100 ,
b100 7
b100 6
b100 ?
#326
0*
b101 ,
b101 7
#327
1*
b110 ,
b110 7
b111 /
b111 9
#328
0*
b111 ,
b111 7
b1001 0
b1001 :
#329
b1000010011100010 @
b100000110001000001 A
b100 C
1!
1*
b1000 ,
b1000 7
#330
0*
#331
b1010010011100010 @
b100000110001000001 A
b100 C
1!
1*
#332
0*
#333
b1010010011100010 @
b100000110001000001 A
b100 C
1!
1*
#334
0*
b0 ,
b0 7
1$
0'
#335
0!
1"
1*
#336
0*
#337
1*
#338
0*
#339
1*
#340
0*
#341
1*
#342
0*
#343
1*
#344
0*
0$
#345
1*
b1 ,
b1 7
#346
0*
b10 ,
b10 7
#347
1*
b11 ,
b11 7
#348
0*
b100 ,
b100 7
#349
1*
b101 ,
b101 7
#350
0*
b110 ,
b110 7
#351
1*
b111 ,
b111 7
b1 0
b1 :
#352
0*
b1000 ,
b1000 7
#353
b1010010011100010 @
b100000110001000001 A
b100 C
1*
#354
0*
#355
b1010010011100010 @
b100000110001000001 A
b100 C
1*
#356
0*
#357
b1010010011100010 @
b100000110001000001 A
b100 C
1*
#358
0*
#359
b1010010011100010 @
b100000110001000001 A
b100 C
1*
#360
0*
#361
b1010010011100010 @
b100000110001000001 A
b100 C
1*
#362
0*
#363
b1010010011100010 @
b100000110001000001 A
b100 C
1*
#364
0*
#365
b1010010011100010 @
b100000110001000001 A
b100 C
1*
#366
0*
#367
b1010010011100010 @
b100000110001000001 A
b100 C
1*
#368
0*
#369
b1010010011100010 @
b100000110001000001 A
b100 C
1*
#370
0*
#371
b1010010011100010 @
b100000110001000001 A
b100 C
1*
#372
0*
b1 ,
b1 7
#373
1*
b10 ,
b10 7
#374
0*
b11 ,
b11 7
#375
1*
b100 ,
b100 7
#376
0*
b101 ,
b101 7
#377
1*
b110 ,
b110 7
#378
0*
b111 ,
b111 7
b1001 0
b1001 :
#379
1!
0"
b11 B
b1010010011100010 @
b100000110001000001 A
b100 C
1*
b1000 ,
b1000 7
#380
0*
#381
1*
#382
0*
#383
1*
#384
0*
b0 ,
b0 7
1$
b101 )
#385
0!
1"
1*
#386
0*
#387
1*
#388
0*
#389
1*
#390
0*
#391
1*
#392
0*
#393
1*
#394
0*
0$
#395
1*
b1 ,
b1 7
b0 3
b0 <
#396
0*
b10 ,
b10 7
b0 4
b0 =
#397
1*
b11 ,
b11 7
b1 5
b1 >
#398
0*
b100 ,
b100 7
b1 6
b1 ?
#399
1*
b101 ,
b101 7
#400
0*
b110 ,
b110 7
b0 /
b0 9
#401
1*
b111 ,
b111 7
b1 0
b1 :
#402
0*
b1000 ,
b1000 7
#403
1!
0"
b0 B
b1010010011100010 @
b100000110001000001 A
b100 C
1*
#404
0*
#405
1*
#406
0*
#407
1*
#408
0*
#409
1*
#410
0*
#411
1*
#412
0*
#413
1*
#414
0*
#415
1*
#416
0*
#417
1*
#418
0*
#419
1*
#420
0*
#421
1*
#422
0*
b0 ,
b0 7
1(
#423
0!
1*
b1 ,
b1 7
b1 3
b1 <
#424
0*
b10 ,
b10 7
b10 4
b10 =
#425
1*
b11 ,
b11 7
b11 5
b11 >
#426
0*
b100 ,
b100 7
b100 6
b100 ?
#427
b10 D
b1010010011100010 @
b100000110001000001 A
b11 C
1!
1*
#428
0*
#429
b1 D
b1010010011100010 @
b100000110001000001 A
b10 C
1!
1*
#430
0*
#431
0!
1*
b0 ,
b0 7
1&
0(
#432
0*
02
b1 ,
b1 7
#433
1*
b10 ,
b10 7
b101 4
b101 =
#434
0*
b11 ,
b11 7
#435
1*
b100 ,
b100 7
#436
0*
b101 ,
b101 7
#437
1*
b110 ,
b110 7
b111 /
b111 9
#438
0*
b111 ,
b111 7
#439
b10 D
1!
1*
b1000 ,
b1000 7
#440
0*
b0 ,
b0 7
1$
0&
#441
0!
1"
1*
#442
0*
#443
1*
#444
0*
#445
1*
#446
0*
#447
1*
#448
0*
#449
1*
#450
0*
0$
#451
1*
b1 ,
b1 7
#452
0*
b10 ,
b10 7
b10 4
b10 =
#453
1*
b11 ,
b11 7
#454
0*
b100 ,
b100 7
#455
1*
b101 ,
b101 7
#456
0*
b110 ,
b110 7
#457
1*
b111 ,
b111 7
b1001 0
b1001 :
#458
0*
b1000 ,
b1000 7
#459
b1000010011100010 @
b100000110010100001 A
b10 C
1*
#460
0*
#461
b1000010011100010 @
b100000110010100001 A
b10 C
1*
#462
0*
#463
1*
b1 ,
b1 7
#464
0*
b10 ,
b10 7
b101 4
b101 =
#465
1*
b11 ,
b11 7
#466
0*
b100 ,
b100 7
#467
1*
b101 ,
b101 7
#468
0*
b110 ,
b110 7
#469
1*
b111 ,
b111 7
b1 0
b1 :
#470
0*
b1000 ,
b1000 7
#471
1!
0"
b1 B
b1000010011100010 @
b100000110010100001 A
b10 C
1*
#472
0*
#473
1*
#474
0*
#475
0!
1"
b1 D
1*
b0 ,
b0 7
1$
#476
0*
#477
1*
#478
0*
#479
1*
#480
0*
#481
1*
#482
0*
#483
1*
#484
0*
#485
1*
0$
#486
0*
#487
1*
#488
0*
#489
1*
#490
0*
b1 ,
b1 7
#491
1*
b10 ,
b10 7
#492
0*
b11 ,
b11 7
#493
1*
b100 ,
b100 7
#494
0*
b101 ,
b101 7
#495
1*
b110 ,
b110 7
#496
0*
b111 ,
b111 7
#497
b1000010000000010 @
b1000010000000000 A
b1 C
1*
b1000 ,
b1000 7
#498
0*
#499
b1 C
1*
#500
0*
