unlocker.v
module unlocker(
    input wire clk, 
    input wire locker, 

    input wire [3:0] inputCount,
    

    input wire [4:0] userNameInput0,
    input wire [4:0] userNameInput1,
    input wire [4:0] userNameInput2,
    input wire [4:0] userNameInput3,

    input wire[4:0] passwordInput0,
    input wire[4:0] passwordInput1,
    input wire[4:0] passwordInput2,
    input wire[4:0] passwordInput3,

    output reg lock
    );

    reg [7:0][19:0] userList;
    reg [7:0][19:0] userPassword;
    reg[19:0] tempUser;
    reg[19:0] tempPassword;

    integer i;

    initial 
    begin
        userList[0][19:0] = 20'b00000000000000000000;
        userPassword[0][19:0] = 20'b00000000000000000000;
        lock = 1;
    end

    always @(posedge clk) 
    begin
        if(inputCount == 8)
        begin
            for(i=0; i<8; i=i+1)
            begin
                tempUser = userList[0][19:0];
                tempPassword = userPassword[0][19:0];
                if(tempUser[4:0] == userNameInput0 && tempUser[9:5] == userNameInput1 && tempUser[14:10] == userNameInput2 && tempUser[19:15] == userNameInput3)
                begin
                    if(tempPassword[4:0] == passwordInput0 && tempPassword[9:5] == passwordInput1 && tempPassword[14:10] == passwordInput2 && tempPassword[19:15] == passwordInput3)
                    begin
                            lock = 0;
                    end
                end
            end
        end
        if(locker)
        begin
            lock = 1;
        end
    end



endmodule

unlocker_tb.v
module unlocker_tb;
    reg clk;
    reg locker;

    reg [3:0] inputCount;

    reg [4:0] userNameInput0;
    reg [4:0] userNameInput1;
    reg [4:0] userNameInput2;
    reg [4:0] userNameInput3;

    reg[4:0] passwordInput0;
    reg[4:0] passwordInput1;
    reg[4:0] passwordInput2;
    reg[4:0] passwordInput3;

    wire lock;


    unlocker my_unlock(
        .clk(clk),
        .locker(locker), 
        .inputCount(inputCount), 
        .userNameInput0(userNameInput0), 
        .userNameInput1(userNameInput1), 
        .userNameInput2(userNameInput2), 
        .userNameInput3(userNameInput3), 
        .passwordInput0(passwordInput0), 
        .passwordInput1(passwordInput1), 
        .passwordInput2(passwordInput2), 
        .passwordInput3(passwordInput3), 
        .lock(lock)
        );

    initial begin
        $dumpfile("wave.vcd");
        $dumpvars(0, unlocker_tb);

        clk = 0;
        #10;
        
        // incorrect password check
        userNameInput0 = 0;
        inputCount = 1;
        #1;
        userNameInput1 = 0;
        inputCount = 2;
        #1;
        userNameInput2 = 1;
        inputCount = 3;
        #1;
        userNameInput3 = 1;
        inputCount = 4;
        
        #1;
        passwordInput0 = 0;
        inputCount = 5;
        #1;
        passwordInput1 = 1;
        inputCount = 6;
        #1;
        passwordInput2 = 1;
        inputCount = 7;
        #1;
        passwordInput3 = 0;
        inputCount = 8;
        #20;

        // correct password check
        userNameInput0 = 0;
        inputCount = 1;
        #1;
        userNameInput1 = 0;
        inputCount = 2;
        #1;
        userNameInput2 = 0;
        inputCount = 3;
        #1;
        userNameInput3 = 0;
        inputCount = 4;
        
        #1;
        passwordInput0 = 0;
        inputCount = 5;
        #1;
        passwordInput1 = 0;
        inputCount = 6;
        #1;
        passwordInput2 = 0;
        inputCount = 7;
        #1;
        passwordInput3 = 0;
        inputCount = 8;
        #20;

        #20 $finish;
    end

    always begin
        #0.5 clk = ~clk;
    end
endmodule

wave.vcd
$date
	Mon Mar  3 11:30:19 2025
$end
$version
	Icarus Verilog
$end
$timescale
	1s
$end
$scope module unlocker_tb $end
$var wire 1 ! lock $end
$var reg 1 " clk $end
$var reg 4 # inputCount [3:0] $end
$var reg 1 $ locker $end
$var reg 5 % passwordInput0 [4:0] $end
$var reg 5 & passwordInput1 [4:0] $end
$var reg 5 ' passwordInput2 [4:0] $end
$var reg 5 ( passwordInput3 [4:0] $end
$var reg 5 ) userNameInput0 [4:0] $end
$var reg 5 * userNameInput1 [4:0] $end
$var reg 5 + userNameInput2 [4:0] $end
$var reg 5 , userNameInput3 [4:0] $end
$scope module my_unlock $end
$var wire 1 " clk $end
$var wire 4 - inputCount [3:0] $end
$var wire 1 $ locker $end
$var wire 5 . passwordInput0 [4:0] $end
$var wire 5 / passwordInput1 [4:0] $end
$var wire 5 0 passwordInput2 [4:0] $end
$var wire 5 1 passwordInput3 [4:0] $end
$var wire 5 2 userNameInput0 [4:0] $end
$var wire 5 3 userNameInput1 [4:0] $end
$var wire 5 4 userNameInput2 [4:0] $end
$var wire 5 5 userNameInput3 [4:0] $end
$var reg 1 ! lock $end
$var reg 20 6 tempPassword [19:0] $end
$var reg 20 7 tempUser [19:0] $end
$var reg 160 8 userList [159:0] $end
$var reg 160 9 userPassword [159:0] $end
$var integer 32 : i [31:0] $end
$upscope $end
$upscope $end
$enddefinitions $end
$comment Show the parameter values. $end
$dumpall
$end
#0
$dumpvars
bx :
bx00000000000000000000 9
bx00000000000000000000 8
bx 7
bx 6
bx 5
bx 4
bx 3
bx 2
bx 1
bx 0
bx /
bx .
bx -
bx ,
bx +
bx *
bx )
bx (
bx '
bx &
bx %
x$
bx #
0"
1!
$end
#1
1"
#2
0"
#3
1"
#4
0"
#5
1"
#6
0"
#7
1"
#8
0"
#9
1"
#10
0"
b1 #
b1 -
b0 )
b0 2
#11
1"
b10 #
b10 -
b0 *
b0 3
#12
0"
b11 #
b11 -
b1 +
b1 4
#13
1"
b100 #
b100 -
b1 ,
b1 5
#14
0"
b101 #
b101 -
b0 %
b0 .
#15
1"
b110 #
b110 -
b1 &
b1 /
#16
0"
b111 #
b111 -
b1 '
b1 0
#17
b0 6
b0 7
b1000 :
1"
b1000 #
b1000 -
b0 (
b0 1
#18
0"
#19
b1000 :
1"
#20
0"
#21
b1000 :
1"
#22
0"
#23
b1000 :
1"
#24
0"
#25
b1000 :
1"
#26
0"
#27
b1000 :
1"
#28
0"
#29
b1000 :
1"
#30
0"
#31
b1000 :
1"
#32
0"
#33
b1000 :
1"
#34
0"
#35
b1000 :
1"
#36
0"
#37
1"
b1 #
b1 -
#38
0"
b10 #
b10 -
#39
1"
b11 #
b11 -
b0 +
b0 4
#40
0"
b100 #
b100 -
b0 ,
b0 5
#41
1"
b101 #
b101 -
#42
0"
b110 #
b110 -
b0 &
b0 /
#43
1"
b111 #
b111 -
b0 '
b0 0
#44
0"
b1000 #
b1000 -
#45
0!
b1000 :
1"
#46
0"
#47
b1000 :
1"
#48
0"
#49
b1000 :
1"
#50
0"
#51
b1000 :
1"
#52
0"
#53
b1000 :
1"
#54
0"
#55
b1000 :
1"
#56
0"
#57
b1000 :
1"
#58
0"
#59
b1000 :
1"
#60
0"
#61
b1000 :
1"
#62
0"
#63
b1000 :
1"
#64
0"
#65
b1000 :
1"
#66
0"
#67
b1000 :
1"
#68
0"
#69
b1000 :
1"
#70
0"
#71
b1000 :
1"
#72
0"
#73
b1000 :
1"
#74
0"
#75
b1000 :
1"
#76
0"
#77
b1000 :
1"
#78
0"
#79
b1000 :
1"
#80
0"
#81
b1000 :
1"
#82
0"
#83
b1000 :
1"
