workingFiles/countDown.v
module countDown(
    input wire clk, // 1hz
    input wire countDownActive,

    output reg [3:0] s10,
    output reg [3:0] s1
    );

    reg [1:0] activeSet;

    initial 
    begin
        activeSet <= 2'b00;
        s10 <= 7;
        s1 <= 9;
    end

    always @(posedge clk) 
    begin
        activeSet <= {activeSet[0], countDownActive};
        if(activeSet == 2'b01)
        begin
            s10 <= 6;
            s1 <= 0;
        end
        else if(countDownActive && ((s1 != 0) || (s10 != 0)))
        begin
            if (s1 === 0)
            begin
                s10 <= s10 - 1;
                s1 <= 9;
            end
            else
            begin
                s1 <= s1 - 1;
            end
        end
        else if(~countDownActive)
        begin
            s10 <= 7;
            s1 <= 9;    
        end
    end



endmodule

workingFiles/display.v
`timescale 10ns / 1ns

module display(
    input wire clk1KHz,
    input wire [3:0] digit1,  // Digit 1 input
    input wire [3:0] digit2,  // Digit 2 input
    input wire [3:0] digit3,  // Digit 3 input
    input wire [3:0] digit4,  // Digit 4 input 
    output reg [3:0] seg,     // 7-segment display output
    output reg [3:0] an       // 4-digit select output (anode control)
);

    reg [1:0] digit_select;   // For digit multiplexing (0: m10, 1: m1, 2: s10, 3: s1)

    // Multiplexing 7-segment decoder
    always @(posedge clk1KHz) begin
        // Check if all digits are zero (no input case)
        // if (digit1 == 4'b0000 && digit2 == 4'b0000 && digit3 == 4'b0000 && digit4 == 4'b0000) begin
        //     seg = 7'b1111111;  // Display nothing (blank) if no input
        // end else begin
            case (digit_select)
                2'b00: begin
                    // Display minutes tens digit (m10)
                    an = 4'b0111;  // Only m10 is active
                    case (digit1)
                        4'b0000: seg = 7'b1000000; // 0
                        4'b0001: seg = 7'b1111001; // 1
                        4'b0010: seg = 7'b0100100; // 2
                        4'b0011: seg = 7'b0110000; // 3
                        4'b0100: seg = 7'b0011001; // 4
                        4'b0101: seg = 7'b0010010; // 5
                        4'b0110: seg = 7'b0000010; // 6
                        4'b0111: seg = 7'b1111000; // 7
                        4'b1000: seg = 7'b0000000; // 8
                        4'b1001: seg = 7'b0010000; // 9
                        4'b1010: seg = 7'b0001000; // A
                        4'b1011: seg = 7'b0000011; // B
                        4'b1100: seg = 7'b1000110; // C
                        4'b1101: seg = 7'b0100001; // D
                        4'b1110: seg = 7'b0000110; // E
                        4'b1111: seg = 7'b0001110; // F
                    endcase
                end
                2'b01: begin
                    // Display minutes ones digit (m1)
                    an = 4'b1011;  // Only m1 is active
                    case (digit2)
                        4'b0000: seg = 7'b1000000;
                        4'b0001: seg = 7'b1111001;
                        4'b0010: seg = 7'b0100100;
                        4'b0011: seg = 7'b0110000;
                        4'b0100: seg = 7'b0011001;
                        4'b0101: seg = 7'b0010010;
                        4'b0110: seg = 7'b0000010;
                        4'b0111: seg = 7'b1111000;
                        4'b1000: seg = 7'b0000000;
                        4'b1001: seg = 7'b0010000;
                        4'b1010: seg = 7'b0001000; // A
                        4'b1011: seg = 7'b0000011; // B
                        4'b1100: seg = 7'b1000110; // C
                        4'b1101: seg = 7'b0100001; // D
                        4'b1110: seg = 7'b0000110; // E
                        4'b1111: seg = 7'b0001110; // F
                    endcase
                end
                2'b10: begin
                    // Display seconds tens digit (s10)
                    an = 4'b1101;  // Only s10 is active
                    case (digit3)
                        4'b0000: seg = 7'b1000000;
                        4'b0001: seg = 7'b1111001;
                        4'b0010: seg = 7'b0100100;
                        4'b0011: seg = 7'b0110000;
                        4'b0100: seg = 7'b0011001;
                        4'b0101: seg = 7'b0010010;
                        4'b0110: seg = 7'b0000010;
                        4'b0111: seg = 7'b1111000;
                        4'b1000: seg = 7'b0000000;
                        4'b1001: seg = 7'b0010000;
                        4'b1010: seg = 7'b0001000; // A
                        4'b1011: seg = 7'b0000011; // B
                        4'b1100: seg = 7'b1000110; // C
                        4'b1101: seg = 7'b0100001; // D
                        4'b1110: seg = 7'b0000110; // E
                        4'b1111: seg = 7'b0001110; // F
                    endcase
                end
                2'b11: begin
                    // Display seconds ones digit (s1)
                    an = 4'b1110;  // Only s1 is active
                    case (digit4)
                        4'b0000: seg = 7'b1000000;
                        4'b0001: seg = 7'b1111001;
                        4'b0010: seg = 7'b0100100;
                        4'b0011: seg = 7'b0110000;
                        4'b0100: seg = 7'b0011001;
                        4'b0101: seg = 7'b0010010;
                        4'b0110: seg = 7'b0000010;
                        4'b0111: seg = 7'b1111000;
                        4'b1000: seg = 7'b0000000;
                        4'b1001: seg = 7'b0010000;
                        4'b1010: seg = 7'b0001000; // A
                        4'b1011: seg = 7'b0000011; // B
                        4'b1100: seg = 7'b1000110; // C
                        4'b1101: seg = 7'b0100001; // D
                        4'b1110: seg = 7'b0000110; // E
                        4'b1111: seg = 7'b0001110; // F
                    endcase
                end
            endcase
        // end
        
        // Cycle through the digits (m10, m1, s10, s1) with multiplexing
        digit_select <= digit_select + 1;
    end
endmodule

workingFiles/displayHandle.v
module displayHandle(
    input wire clk, // 1hz
    input wire clk1KHz, //1khz
    input wire flag,
    input wire flagSelect,
    input wire lock,

    output reg flagResolve,
    output reg locker,

    output wire [3:0] seg,     // 7-segment display output
    output wire [3:0] an       // 4-digit select output (anode control)
    );

    reg prevLockState;

    reg countDownActive;
    wire [3:0] s10;
    wire [3:0] s1;

    reg smallDisplay10;
    reg smallDisplay1;

    display my_Display(
        .clk1KHz(clk1KHz),
        .digit1(4'b0000),  // Digit 1 input
        .digit2(4'b0000),  // Digit 2 input
        .digit3(s10),  // Digit 3 input
        .digit4(s1),  // Digit 4 input 
        .seg(seg),     // 7-segment display output
        .an(an)       // 4-digit select output (anode control)
    );

    countDown my_CountDown(
        .clk(clk), // 1hz
        .countDownActive(countDownActive),

        .s10(s10),
        .s1(s1)
    );

    initial 
    begin
        flagResolve <= 0;
        countDownActive <= 0;
        locker <= 0;
        smallDisplay10 <= 1;
        smallDisplay1 <= 1;
        prevLockState <= 1;
    end

    always @(posedge clk) 
    begin
        prevLockState <= lock;
       if(flag && ~flagSelect)
       begin
            // wrong password 
            smallDisplay10 <= 0;
            smallDisplay1 <= 0;

            flagResolve <= 1;
       end
       else if(flag && flagSelect && ~flagResolve)
       begin
            // 3 failed attempts 
            if(~countDownActive)
            begin
                countDownActive <= 1;
                smallDisplay10 <= 0;
                smallDisplay1 <= 0;
                $display("Count down activated");
            end
            else if(s10 == 0 && s1 == 0)
            begin   
                smallDisplay10 <= 1;
                smallDisplay1 <= 1;
                flagResolve <= 1;
                countDownActive <= 0;
            end
       end
       else
       begin
            flagResolve <= 0;
       end

       if (~lock && ~locker) begin
            if(~countDownActive)
            begin
                smallDisplay10 <= 0;
                smallDisplay1 <= 1;
                countDownActive <= 1;
            end
            else if(s10 == 0 && s1 == 0)
            begin   
                locker <= 1;
                smallDisplay10 <= 1;
                smallDisplay1 <= 1;
                countDownActive <= 0;
            end
       end
       else if(~prevLockState && lock)
       begin
            smallDisplay10 <= 1;
            smallDisplay1 <= 1;
       end
       else
        begin
            locker <= 0;
        end
    end



endmodule

workingFiles/unlocker.v
module unlocker(
    input wire clk, 
    input wire locker, 

    input wire btn1,
    input wire btn2,
    input wire btn3,
    input wire btn4,
    input wire btn5,
    input wire switch1, // ==0 : guest account // ==1 : user account 

    input wire [3:0] inputCount,
    

    input wire [3:0] userNameInput0,
    input wire [3:0] userNameInput1,
    input wire [3:0] userNameInput2,
    input wire [3:0] userNameInput3,

    input wire[3:0] passwordInput0,
    input wire[3:0] passwordInput1,
    input wire[3:0] passwordInput2,
    input wire[3:0] passwordInput3,

    input wire flagResolve, //indicates that the flag has been delt with 

    output reg lock,
    output reg flag,        //when flag goes up error = incorrect password 
    output reg flagSelect,     //flagSelect = 0: wrong password attempt, flagSelect = 1: 3 incorrect attempts 
    output reg resetCount   //tell other module to reset inputCount to 0, also means input is not going to get read

    );

    reg [15:0] userList [7:0];    // Array of 8 elements, each 20 bits wide
    reg [15:0] userPassword [7:0]; // Array of 8 elements, each 20 bits wide
    reg [1:0] userMode [7:0];      // 0=admin, 1=user, 2=guest

    reg[15:0] tempUser;
    reg[15:0] tempPassword;

    integer userCount;
    
    integer currentUser;

    integer loginAttempts;

    integer i;

    initial 
    begin
        for(i=0; i<8; i=i+1)
        begin
            userList[i] <= 16'b0000000000000000;
            userPassword[i] <= 16'b0000000000000000;
            userMode[i] <= 2'b00;
        end
        currentUser <= 0;
        userCount <= 1;
        lock <= 1;
        loginAttempts <= 0;
        flag <= 0;
        flagSelect <= 0;
    end

    always @(posedge clk) 
    begin
        if(flag)
        begin
            if(flagResolve)
            begin
                flagSelect <= 0;
                flag <= 0;
            end
        end
        else if(~lock)
        begin
            if(locker || btn1)
            begin
                if(userMode[currentUser] == 2)
                begin
                    // remove current user 
                    userCount <= userCount - 1;
                    userList[currentUser][15:0] <= userList[userCount][15:0];
                    userPassword[currentUser][15:0] <= userPassword[userCount][15:0];
                    userMode[currentUser] <= userMode[userCount];

                    userList[userCount][15:0] <= 16'b0000000000000000;
                    userPassword[userCount][15:0] <= 16'b0000000000000000;
                    userMode[userCount] <= 2'b00;
                end
                lock <= 1;
                resetCount <= 0;
            end
            else if(userMode[currentUser][1:0] == 2'b00 || userMode[currentUser][1:0] == 2'b01)
            begin
                if(btn2)
                begin
                    // reset password
                    resetCount <= 0;
                    if(inputCount >= 4)
                    begin
                        userPassword[currentUser][15:0] <= {userNameInput3[3:0], userNameInput2[3:0], userNameInput1[3:0], userNameInput0[3:0]};
                        // $display("New password: %b", userPassword[currentUser][15:0]);
                        resetCount <= 1;
                    end
                    
                    
                end
                else if(userMode[currentUser][1:0] == 2'b00)
                begin
                    if(btn3)
                    begin
                        // add user 
                        resetCount <= 0;
                        if(inputCount == 8)
                        begin
                            if(userCount < 8)
                            begin
                                userList[userCount] <= {userNameInput3[3:0], userNameInput2[3:0], userNameInput1[3:0], userNameInput0[3:0]};
                                userPassword[userCount] <= {passwordInput3[3:0], passwordInput2[3:0], passwordInput1[3:0], passwordInput0[3:0]};
                                if(switch1)
                                begin
                                    userMode[userCount] <= 1;
                                end
                                else
                                begin
                                    userMode[userCount] <= 2;
                                end
                                resetCount <= 1;
                                userCount <= userCount + 1;
                            end
                            else
                            begin
                                // alert too many usres
                                // flag <= 1;
                            end
                        end
                    end
                    else if(btn4)
                    begin
                        // change password
                        resetCount <= 0;
                        if(inputCount == 8)
                        begin
                            resetCount <= 1;
                            for(i=0; i<8; i=i+1)
                            begin
                                tempUser = userList[i][15:0];
                                tempPassword = userPassword[i][15:0];
                                if(tempUser[3:0] == userNameInput0 && tempUser[7:4] == userNameInput1 && tempUser[11:8] == userNameInput2 && tempUser[15:12] == userNameInput3)
                                begin
                                    userPassword[i] <= {passwordInput3[3:0], passwordInput2[3:0], passwordInput1[3:0], passwordInput0[3:0]};
                                end
                            end
                        end

                    end
                    else if(btn5)
                    begin
                        // delete user 
                        resetCount <= 0;
                        if(inputCount == 4)
                        begin
                            resetCount <= 1;
                            for(i=0; i<8; i=i+1)
                            begin
                                tempUser <= userList[i][15:0];
                                tempPassword <= userPassword[i][15:0];
                                if(tempUser[3:0] == userNameInput0 && tempUser[7:4] == userNameInput1 && tempUser[11:8] == userNameInput2 && tempUser[15:12] == userNameInput3)
                                begin
                                    userCount <= userCount - 1;
                                    userList[i][15:0] <= userList[userCount][15:0];
                                    userPassword[i][15:0] <= userPassword[userCount][15:0];
                                    userMode[i] <= userMode[userCount];

                                    userList[userCount][15:0] <= 16'b0000000000000000;
                                    userPassword[userCount][15:0] <= 16'b0000000000000000;
                                    userMode[userCount] <= 2'b00;
                                end
                            end
                        end
                    end
                end
            end
        end
        else if(inputCount == 8)
        begin
            for(i=0; i<8; i=i+1)
            begin
                tempUser = userList[i][15:0];
                tempPassword = userPassword[i][15:0];
                if(tempUser[3:0] == userNameInput0 && tempUser[7:4] == userNameInput1 && tempUser[11:8] == userNameInput2 && tempUser[15:12] == userNameInput3)
                begin
                    if(tempPassword[3:0] == passwordInput0 && tempPassword[7:4] == passwordInput1 && tempPassword[11:8] == passwordInput2 && tempPassword[15:12] == passwordInput3)
                    begin
                        currentUser <= i;
                        lock <= 0;
                        resetCount <= 1;
                        loginAttempts <= 0;
                        $display("Successful attempt");
                    end
                    else
                    begin
                        $display("Failed attempt");
                        flag <= 1;
                        if(loginAttempts == 2)
                        begin
                            flagSelect <= 1;
                            loginAttempts <= 0;
                        end
                        else
                        begin
                            loginAttempts <= loginAttempts + 1;
                            flagSelect <= 0;
                        end
                    end;
                end
            end
        end
        
    end



endmodule

workingFiles/displayHandle_tb.v
module displayHandle_tb;
    reg clk;
    wire locker;

    reg btn1;
    reg btn2;
    reg btn3;
    reg btn4;
    reg btn5;

    reg switch1;

    reg [3:0] inputCount;

    reg [3:0] userNameInput0;
    reg [3:0] userNameInput1;
    reg [3:0] userNameInput2;
    reg [3:0] userNameInput3;

    reg[3:0] passwordInput0;
    reg[3:0] passwordInput1;
    reg[3:0] passwordInput2;
    reg[3:0] passwordInput3;

    wire flagResolve;

    wire lock;
    wire flag;
    wire flagSelect;
    wire resetCount;

    wire [3:0] seg;     // 7-segment display output
    wire [3:0] an;       // 4-digit select output (anode control)

    reg[3:0] checkCount;

    unlocker my_unlock(
        .clk(clk),
        .locker(locker), 
        .btn1(btn1),
        .btn2(btn2),
        .btn3(btn3),
        .btn4(btn4),
        .btn5(btn5),
        .switch1(switch1),
        .inputCount(inputCount), 
        .userNameInput0(userNameInput0), 
        .userNameInput1(userNameInput1), 
        .userNameInput2(userNameInput2), 
        .userNameInput3(userNameInput3), 
        .passwordInput0(passwordInput0), 
        .passwordInput1(passwordInput1), 
        .passwordInput2(passwordInput2), 
        .passwordInput3(passwordInput3), 
        .flagResolve(flagResolve),
        .lock(lock),
        .flag(flag),
        .flagSelect(flagSelect),
        .resetCount(resetCount)
    );

    displayHandle myDisplayHandle(
        .clk(clk),
        .clk1KHz(clk),
        .flag(flag),
        .flagSelect(flagSelect),
        .lock(lock),

        .flagResolve(flagResolve),
        .locker(locker),
        .seg(seg),     // 7-segment display output
        .an(an)        // 4-digit select output
    );

    initial begin
        $dumpfile("wave.vcd");
        $dumpvars(0, displayHandle_tb);
        $display("Waveform created");

        clk = 0;
        checkCount = 1;
        //== incorrect password check ==//
        userNameInput0 = 0;
        inputCount = 1;
        #1;
        userNameInput1 = 0;
        inputCount = 2;
        #1;
        userNameInput2 = 1;
        inputCount = 3;
        #1;
        userNameInput3 = 1;
        inputCount = 4;
        
        #1;
        passwordInput0 = 1;
        inputCount = 5;
        #1;
        passwordInput1 = 0;
        inputCount = 6;
        #1;
        passwordInput2 = 1;
        inputCount = 7;
        #1;
        passwordInput3 = 1;
        inputCount = 8;
        #1;

        checkCount = 2;
        //== lockout check ==//
        //incorrect 1
        userNameInput0 = 0;
        inputCount = 1;
        #1;
        userNameInput1 = 0;
        inputCount = 2;
        #1;
        userNameInput2 = 1;
        inputCount = 3;
        #1;
        userNameInput3 = 1;
        inputCount = 4;
        
        #1;
        passwordInput0 = 1;
        inputCount = 5;
        #1;
        passwordInput1 = 0;
        inputCount = 6;
        #1;
        passwordInput2 = 1;
        inputCount = 7;
        #1;
        passwordInput3 = 1;
        inputCount = 8;
        #1;

        //incorrect 2
        userNameInput0 = 0;
        inputCount = 1;
        #1;
        userNameInput1 = 0;
        inputCount = 2;
        #1;
        userNameInput2 = 1;
        inputCount = 3;
        #1;
        userNameInput3 = 1;
        inputCount = 4;
        
        #1;
        passwordInput0 = 1;
        inputCount = 5;
        #1;
        passwordInput1 = 0;
        inputCount = 6;
        #1;
        passwordInput2 = 1;
        inputCount = 7;
        #1;
        passwordInput3 = 1;
        inputCount = 8;
        #1;

        //incorrect 3
        userNameInput0 = 0;
        inputCount = 1;
        #1;
        userNameInput1 = 0;
        inputCount = 2;
        #1;
        userNameInput2 = 1;
        inputCount = 3;
        #1;
        userNameInput3 = 1;
        inputCount = 4;
        
        #1;
        passwordInput0 = 1;
        inputCount = 5;
        #1;
        passwordInput1 = 0;
        inputCount = 6;
        #1;
        passwordInput2 = 1;
        inputCount = 7;
        #1;
        passwordInput3 = 1;
        inputCount = 8;
        #1;
        inputCount = 0;

        checkCount = checkCount + 1;
        //==check to see if use is locked out, should keep user locked out
        userNameInput0 = 0;
        inputCount = 1;
        #1;
        userNameInput1 = 0;
        inputCount = 2;
        #1;
        userNameInput2 = 1;
        inputCount = 3;
        #1;
        userNameInput3 = 1;
        inputCount = 4;
        
        #1;
        passwordInput0 = 0;
        inputCount = 5;
        #1;
        passwordInput1 = 0;
        inputCount = 6;
        #1;
        passwordInput2 = 1;
        inputCount = 7;
        #1;
        passwordInput3 = 1;
        inputCount = 8;
        #1;
        inputCount = 0;

        checkCount = checkCount + 1;
        //==log in after, and start count down for auto lock
        #150;
        inputCount = 8;
        #2;
        inputCount = 0;
        #150;
        


        #15 $finish;
    end

    always begin
        #0.5 clk = ~clk;
    end
endmodule

workingFiles/wave.vcd
$date
	Mon Mar 10 17:51:15 2025
$end
$version
	Icarus Verilog
$end
$timescale
	1ns
$end
$scope module displayHandle_tb $end
$var wire 4 ! seg [3:0] $end
$var wire 1 " resetCount $end
$var wire 1 # locker $end
$var wire 1 $ lock $end
$var wire 1 % flagSelect $end
$var wire 1 & flagResolve $end
$var wire 1 ' flag $end
$var wire 4 ( an [3:0] $end
$var reg 1 ) btn1 $end
$var reg 1 * btn2 $end
$var reg 1 + btn3 $end
$var reg 1 , btn4 $end
$var reg 1 - btn5 $end
$var reg 4 . checkCount [3:0] $end
$var reg 1 / clk $end
$var reg 4 0 inputCount [3:0] $end
$var reg 4 1 passwordInput0 [3:0] $end
$var reg 4 2 passwordInput1 [3:0] $end
$var reg 4 3 passwordInput2 [3:0] $end
$var reg 4 4 passwordInput3 [3:0] $end
$var reg 1 5 switch1 $end
$var reg 4 6 userNameInput0 [3:0] $end
$var reg 4 7 userNameInput1 [3:0] $end
$var reg 4 8 userNameInput2 [3:0] $end
$var reg 4 9 userNameInput3 [3:0] $end
$scope module myDisplayHandle $end
$var wire 1 / clk $end
$var wire 1 / clk1KHz $end
$var wire 4 : seg [3:0] $end
$var wire 4 ; s10 [3:0] $end
$var wire 4 < s1 [3:0] $end
$var wire 1 $ lock $end
$var wire 1 % flagSelect $end
$var wire 1 ' flag $end
$var wire 4 = an [3:0] $end
$var reg 1 > countDownActive $end
$var reg 1 & flagResolve $end
$var reg 1 # locker $end
$var reg 1 ? prevLockState $end
$var reg 1 @ smallDisplay1 $end
$var reg 1 A smallDisplay10 $end
$scope module my_CountDown $end
$var wire 1 / clk $end
$var wire 1 > countDownActive $end
$var reg 2 B activeSet [1:0] $end
$var reg 4 C s1 [3:0] $end
$var reg 4 D s10 [3:0] $end
$upscope $end
$scope module my_Display $end
$var wire 1 / clk1KHz $end
$var wire 4 E digit1 [3:0] $end
$var wire 4 F digit2 [3:0] $end
$var wire 4 G digit3 [3:0] $end
$var wire 4 H digit4 [3:0] $end
$var reg 4 I an [3:0] $end
$var reg 2 J digit_select [1:0] $end
$var reg 4 K seg [3:0] $end
$upscope $end
$upscope $end
$scope module my_unlock $end
$var wire 1 ) btn1 $end
$var wire 1 * btn2 $end
$var wire 1 + btn3 $end
$var wire 1 , btn4 $end
$var wire 1 - btn5 $end
$var wire 1 / clk $end
$var wire 1 & flagResolve $end
$var wire 4 L inputCount [3:0] $end
$var wire 1 # locker $end
$var wire 4 M passwordInput0 [3:0] $end
$var wire 4 N passwordInput1 [3:0] $end
$var wire 4 O passwordInput2 [3:0] $end
$var wire 4 P passwordInput3 [3:0] $end
$var wire 1 5 switch1 $end
$var wire 4 Q userNameInput0 [3:0] $end
$var wire 4 R userNameInput1 [3:0] $end
$var wire 4 S userNameInput2 [3:0] $end
$var wire 4 T userNameInput3 [3:0] $end
$var reg 1 ' flag $end
$var reg 1 % flagSelect $end
$var reg 1 $ lock $end
$var reg 1 " resetCount $end
$var reg 16 U tempPassword [15:0] $end
$var reg 16 V tempUser [15:0] $end
$var integer 32 W currentUser [31:0] $end
$var integer 32 X i [31:0] $end
$var integer 32 Y loginAttempts [31:0] $end
$var integer 32 Z userCount [31:0] $end
$upscope $end
$upscope $end
$enddefinitions $end
$comment Show the parameter values. $end
$dumpall
$end
#0
$dumpvars
b1 Z
b0 Y
bx X
b0 W
bx V
bx U
bx T
bx S
bx R
b0 Q
bx P
bx O
bx N
bx M
b1 L
bx K
bx J
bx I
b1001 H
b111 G
b0 F
b0 E
b111 D
b1001 C
b0 B
1A
1@
1?
0>
bx =
b1001 <
b111 ;
bx :
bx 9
bx 8
bx 7
b0 6
x5
bx 4
bx 3
bx 2
bx 1
b1 0
0/
b1 .
x-
x,
x+
x*
x)
bx (
0'
0&
0%
1$
0#
x"
bx !
$end
#5
1/
#10
0/
b10 0
b10 L
b0 7
b0 R
#15
1/
#20
0/
b11 0
b11 L
b1 8
b1 S
#25
1/
#30
0/
b100 0
b100 L
b1 9
b1 T
#35
1/
#40
0/
b101 0
b101 L
b1 1
b1 M
#45
1/
#50
0/
b110 0
b110 L
b0 2
b0 N
#55
1/
#60
0/
b111 0
b111 L
b1 3
b1 O
#65
1/
#70
0/
b1000 0
b1000 L
b1 4
b1 P
#75
b1000100000000 U
b1000100000000 V
b1 X
1/
#80
0/
b1 0
b1 L
b10 .
#85
1/
#90
0/
b10 0
b10 L
#95
1/
#100
0/
b11 0
b11 L
#105
1/
#110
0/
b100 0
b100 L
#115
1/
#120
0/
b101 0
b101 L
#125
1/
#130
0/
b110 0
b110 L
#135
1/
#140
0/
b111 0
b111 L
#145
1/
#150
0/
b1000 0
b1000 L
#155
b1 Y
1'
b1 X
1/
#160
0/
b1 0
b1 L
#165
1&
0@
0A
1/
#170
0/
b10 0
b10 L
#175
0'
1/
#180
0/
b11 0
b11 L
#185
0&
1/
#190
0/
b100 0
b100 L
#195
1/
#200
0/
b101 0
b101 L
#205
1/
#210
0/
b110 0
b110 L
#215
1/
#220
0/
b111 0
b111 L
#225
1/
#230
0/
b1000 0
b1000 L
#235
b10 Y
1'
b1 X
1/
#240
0/
b1 0
b1 L
#245
1&
1/
#250
0/
b10 0
b10 L
#255
0'
1/
#260
0/
b11 0
b11 L
#265
0&
1/
#270
0/
b100 0
b100 L
#275
1/
#280
0/
b101 0
b101 L
#285
1/
#290
0/
b110 0
b110 L
#295
1/
#300
0/
b111 0
b111 L
#305
1/
#310
0/
b1000 0
b1000 L
#315
b0 Y
1%
1'
b1 X
1/
#320
0/
b11 .
b1 0
b1 L
#325
1>
1/
#330
0/
b10 0
b10 L
#335
b1000 <
b1000 C
b1000 H
b1 B
1/
#340
0/
b11 0
b11 L
#345
b0 <
b0 C
b0 H
b110 ;
b110 D
b110 G
b11 B
1/
#350
0/
b100 0
b100 L
#355
b1001 <
b1001 C
b1001 H
b101 ;
b101 D
b101 G
1/
#360
0/
b101 0
b101 L
b0 1
b0 M
#365
b1000 <
b1000 C
b1000 H
1/
#370
0/
b110 0
b110 L
#375
b111 <
b111 C
b111 H
1/
#380
0/
b111 0
b111 L
#385
b110 <
b110 C
b110 H
1/
#390
0/
b1000 0
b1000 L
#395
b101 <
b101 C
b101 H
1/
#400
0/
b100 .
b0 0
b0 L
#405
b100 <
b100 C
b100 H
1/
#410
0/
#415
b11 <
b11 C
b11 H
1/
#420
0/
#425
b10 <
b10 C
b10 H
1/
#430
0/
#435
b1 <
b1 C
b1 H
1/
#440
0/
#445
b0 <
b0 C
b0 H
1/
#450
0/
#455
b1001 <
b1001 C
b1001 H
b100 ;
b100 D
b100 G
1/
#460
0/
#465
b1000 <
b1000 C
b1000 H
1/
#470
0/
#475
b111 <
b111 C
b111 H
1/
#480
0/
#485
b110 <
b110 C
b110 H
1/
#490
0/
#495
b101 <
b101 C
b101 H
1/
#500
0/
#505
b100 <
b100 C
b100 H
1/
#510
0/
#515
b11 <
b11 C
b11 H
1/
#520
0/
#525
b10 <
b10 C
b10 H
1/
#530
0/
#535
b1 <
b1 C
b1 H
1/
#540
0/
#545
b0 <
b0 C
b0 H
1/
#550
0/
#555
b1001 <
b1001 C
b1001 H
b11 ;
b11 D
b11 G
1/
#560
0/
#565
b1000 <
b1000 C
b1000 H
1/
#570
0/
#575
b111 <
b111 C
b111 H
1/
#580
0/
#585
b110 <
b110 C
b110 H
1/
#590
0/
#595
b101 <
b101 C
b101 H
1/
#600
0/
#605
b100 <
b100 C
b100 H
1/
#610
0/
#615
b11 <
b11 C
b11 H
1/
#620
0/
#625
b10 <
b10 C
b10 H
1/
#630
0/
#635
b1 <
b1 C
b1 H
1/
#640
0/
#645
b0 <
b0 C
b0 H
1/
#650
0/
#655
b1001 <
b1001 C
b1001 H
b10 ;
b10 D
b10 G
1/
#660
0/
#665
b1000 <
b1000 C
b1000 H
1/
#670
0/
#675
b111 <
b111 C
b111 H
1/
#680
0/
#685
b110 <
b110 C
b110 H
1/
#690
0/
#695
b101 <
b101 C
b101 H
1/
#700
0/
#705
b100 <
b100 C
b100 H
1/
#710
0/
#715
b11 <
b11 C
b11 H
1/
#720
0/
#725
b10 <
b10 C
b10 H
1/
#730
0/
#735
b1 <
b1 C
b1 H
1/
#740
0/
#745
b0 <
b0 C
b0 H
1/
#750
0/
#755
b1001 <
b1001 C
b1001 H
b1 ;
b1 D
b1 G
1/
#760
0/
#765
b1000 <
b1000 C
b1000 H
1/
#770
0/
#775
b111 <
b111 C
b111 H
1/
#780
0/
#785
b110 <
b110 C
b110 H
1/
#790
0/
#795
b101 <
b101 C
b101 H
1/
#800
0/
#805
b100 <
b100 C
b100 H
1/
#810
0/
#815
b11 <
b11 C
b11 H
1/
#820
0/
#825
b10 <
b10 C
b10 H
1/
#830
0/
#835
b1 <
b1 C
b1 H
1/
#840
0/
#845
b0 <
b0 C
b0 H
1/
#850
0/
#855
b1001 <
b1001 C
b1001 H
b0 ;
b0 D
b0 G
1/
#860
0/
#865
b1000 <
b1000 C
b1000 H
1/
#870
0/
#875
b111 <
b111 C
b111 H
1/
#880
0/
#885
b110 <
b110 C
b110 H
1/
#890
0/
#895
b101 <
b101 C
b101 H
1/
#900
0/
#905
b100 <
b100 C
b100 H
1/
#910
0/
#915
b11 <
b11 C
b11 H
1/
#920
0/
#925
b10 <
b10 C
b10 H
1/
#930
0/
#935
b1 <
b1 C
b1 H
1/
#940
0/
#945
b0 <
b0 C
b0 H
1/
#950
0/
#955
0>
1&
1@
1A
1/
#960
0/
#965
0'
0%
b1001 <
b1001 C
b1001 H
b111 ;
b111 D
b111 G
b10 B
0&
1/
#970
0/
#975
b0 B
1/
